{
"meta":{"test_sets":[],"test_metrics":[],"learn_metrics":[{"best_value":"Min","name":"RMSE"}],"launch_mode":"Train","parameters":"","iteration_count":1000,"learn_sets":["learn"],"name":"experiment"},
"iterations":[
{"learn":[0.6118699461],"iteration":0,"passed_time":0.007124291607,"remaining_time":7.117167316},
{"learn":[0.5984132512],"iteration":1,"passed_time":0.01214129358,"remaining_time":6.058505498},
{"learn":[0.5856984574],"iteration":2,"passed_time":0.01735970631,"remaining_time":5.769209062},
{"learn":[0.5720132659],"iteration":3,"passed_time":0.022736473,"remaining_time":5.661381777},
{"learn":[0.5593634913],"iteration":4,"passed_time":0.02751960337,"remaining_time":5.476401071},
,
{"learn":[0.5492205229],"iteration":5,"passed_time":0.03292957718,"remaining_time":5.45533328,
,
{"learn":[0.5373273286],"iteration":6,"passed_time":0.03867085651,"remaining_time":5.48573721,
,
{"learn":[0.5252438702],"iteration":7,"passed_time":0.04466074491,"remaining_time":5.53793236,
,
{"learn":[0.5140048122],"iteration":8,"passed_time":0.05073459984,"remaining_time":5.58644316,,
{"learn":[0.5039288338],"iteration":9,"passed_time":0.05550252143,"remaining_time":5.494749621,,
{"learn":[0.4950300606],"iteration":10,"passed_time":0.06156574404,"remaining_time":5.535320078,,
{"learn":[0.4847833706],"iteration":11,"passed_time":0.06688014221,"remaining_time":5.50646504,
,
{"learn":[0.4752903352],"iteration":12,"passed_time":0.07162820381,"remaining_time":5.4382336,
{,
{"learn":[0.4657450556],"iteration":13,"passed_time":0.07565179476,"remaining_time":5.3280478,
{,
{"learn":[0.4565997163],"iteration":14,"passed_time":0.08155044294,"remaining_time":5.355145,,
{,
{"learn":[0.4470883732],"iteration":15,"passed_time":0.08679382563,"remaining_time":5.33782,
,
{,
{"learn":[0.4393703183],"iteration":16,"passed_time":0.09135972018,"remaining_time":5.28274,
,
{,
{"learn":[0.4315910999],"iteration":17,"passed_time":0.09668296788,"remaining_time":5.27459,
,
{,
{"learn":[0.4238548849],"iteration":18,"passed_time":0.1021902406,"remaining_time":5.276243,
{",
{"learn":[0.4157209312],"iteration":19,"passed_time":0.1081681185,"remaining_time":5.300237,
{",
{"learn":[0.4072903369],"iteration":20,"passed_time":0.1137144472,"remaining_time":5.301259,
{",
{"learn":[0.3994789091],"iteration":21,"passed_time":0.1196388851,"remaining_time":5.318492,
{",
{"learn":[0.3919886056],"iteration":22,"passed_time":0.1253779957,"remaining_time":5.325839,
{",
{"learn":[0.3839531525],"iteration":23,"passed_time":0.1304591859,"remaining_time":5.30534,
{"l,
{"learn":[0.3777684959],"iteration":24,"passed_time":0.1355149948,"remaining_time":5.28508,
{"l,
{"learn":[0.3701242161],"iteration":25,"passed_time":0.1406238346,"remaining_time":5.26798,
{"l,
{"learn":[0.363754624],"iteration":26,"passed_time":0.1455806781,"remaining_time":5.246296,
{",
{"learn":[0.3570024047],"iteration":27,"passed_time":0.1503327694,"remaining_time":5.218694,
{",
{"learn":[0.3519864404],"iteration":28,"passed_time":0.1555033865,"remaining_time":5.206682,
{",
{"learn":[0.3460109812],"iteration":29,"passed_time":0.1604037746,"remaining_time":5.18638,,
{",
{"learn":[0.3401644494],"iteration":30,"passed_time":0.1652055073,"remaining_time":5.164,
,,
{",
{"learn":[0.3349765837],"iteration":31,"passed_time":0.1709744425,"remaining_time":5.17,
{,,
{",
{"learn":[0.3303376213],"iteration":32,"passed_time":0.1764122465,"remaining_time":5.16,
{,,
{",
{"learn":[0.3247643729],"iteration":33,"passed_time":0.1816769381,"remaining_time":5.1617,
{"le,
{"learn":[0.3196760025],"iteration":34,"passed_time":0.1864374651,"remaining_time":5.,
{",
{"le,
{"learn":[0.3146802728],"iteration":35,"passed_time":0.1908194973,"remaining_time",
{"le,,
{"le,
{"learn":[0.3096293353],"iteration":36,"passed_time":0.1970505056,"remaining_time,
{"lea,
{"lea,
{"learn":[0.30535164],"iteration":37,"passed_time":0.2035420955,"remaining_time":,
{"lea,
{"l,
{"learn":[0.3011398611],"iteration":38,"passed_time":0.2095127484,"remaining_time":,
{"le,
{"le,
{"learn":[0.2970699388],"iteration":39,"passed_time":0.2136272777,"remaining_time":,
{",
{"lear,
{"learn":[0.2928269459],"iteration":40,"passed_time":0.2216018988,"remaining_time":5.18,
{"lear,
{"learn":[0.2887661306],"iteration":41,"passed_time":0.2274397001,"remaining_time":,
{,
{"learn,
{"learn":[0.2845955353],"iteration":42,"passed_time":0.2334496301,"remaining_time":5.1,
{"learn,
{"learn":[0.2799742479],"iteration":43,"passed_time":0.2392732908,"remaining_time":5.1,
{"learn,
{"learn":[0.2767621824],"iteration":44,"passed_time":0.2453410594,"remaining_time":5.2,
{"learn,
{"learn":[0.2731684379],"iteration":45,"passed_time":0.2508395347,"remaining_time":5.2,
{"learn,
{"learn":[0.2696055632],"iteration":46,"passed_time":0.2570274889,"remaining_time":5.2,
{"learn,
{"learn":[0.2664785705],"iteration":47,"passed_time":0.2629753475,"remaining_time":5.215677726},
{"learn":[0.2629112321],"iteration":48,"passed_time":0.2688970922,"remaining_time":5.218798668},
{"learn":[0.2597644959],"iteration":49,"passed_time":0.2736838522,"remaining_time":5.199993191},
{"learn":[0.2566008646],"iteration":50,"passed_time":0.2803838953,"remaining_time":5.217339543},
{"learn":[0.25361593],"iteration":51,"passed_time":0.2863009509,"remaining_time":5.219486566},
{"learn":[0.2508393867],"iteration":52,"passed_time":0.2922722674,"remaining_time":5.222298816},
{"learn":[0.2481990735],"iteration":53,"passed_time":0.2970584832,"remaining_time":5.204024539},
{"learn":[0.2456422599],"iteration":54,"passed_time":0.3019741738,"remaining_time":5.188465349},
{"learn":[0.2429240588],"iteration":55,"passed_time":0.3068642741,"remaining_time":5.172854907},
{"learn":[0.2403230115],"iteration":56,"passed_time":0.3123019874,"remaining_time":5.166680247},
{"learn":[0.2377465176],"iteration":57,"passed_time":0.3170089534,"remaining_time":5.148662657},
{"learn":[0.2352227233],"iteration":58,"passed_time":0.3222566081,"remaining_time":5.1397198},
{"learn":[0.2327959453],"iteration":59,"passed_time":0.3276544483,"remaining_time":5.133253024},
{"learn":[0.230498067],"iteration":60,"passed_time":0.3333529591,"remaining_time":5.131449649},
{"learn":[0.2288763503],"iteration":61,"passed_time":0.3398978275,"remaining_time":5.142325196},
{"learn":[0.2265811477],"iteration":62,"passed_time":0.3467108329,"remaining_time":5.156635721},
{"learn":[0.2246350711],"iteration":63,"passed_time":0.3538511266,"remaining_time":5.175072727},
{"learn":[0.2227048608],"iteration":64,"passed_time":0.3592907116,"remaining_time":5.168258698},
{"learn":[0.2210925837],"iteration":65,"passed_time":0.3651193909,"remaining_time":5.166992593},
{"learn":[0.2192905058],"iteration":66,"passed_time":0.369585607,"remaining_time":5.146617482},
{"learn":[0.2174487701],"iteration":67,"passed_time":0.3761048394,"remaining_time":5.154848681},
{"learn":[0.2155114683],"iteration":68,"passed_time":0.3818332856,"remaining_time":5.151982448},
{"learn":[0.2136935694],"iteration":69,"passed_time":0.3871092561,"remaining_time":5.143022973},
{"learn":[0.212011483],"iteration":70,"passed_time":0.392536168,"remaining_time":5.136142255},
{"learn":[0.2103254012],"iteration":71,"passed_time":0.3974359658,"remaining_time":5.122508003},
{"learn":[0.2083746293],"iteration":72,"passed_time":0.4035608109,"remaining_time":5.124669476},
{"learn":[0.2069252056],"iteration":73,"passed_time":0.409429173,"remaining_time":5.123397489},
{"learn":[0.2054314699],"iteration":74,"passed_time":0.4151657877,"remaining_time":5.120378048},
{"learn":[0.2038477903],"iteration":75,"passed_time":0.4204578966,"remaining_time":5.,
{"learn",
{"learn":[0.2023635457],"iteration":76,"passed_time":0.4249028555,"remaining_time":5.,
{"learn",
{"learn":[0.2008539986],"iteration":77,"passed_time":0.4288882922,"remaining_time":,
{"learn":[,
{"learn":[0.1994740637],"iteration":78,"passed_time":0.4350049671,"remaining_time":,
{"learn":[,
{"learn":[0.1984362084],"iteration":79,"passed_time":0.4403973868,"remaining_time":,
{"learn":[,
{"learn":[0.1973176934],"iteration":80,"passed_time":0.4453060293,"remaining_time":,
{"learn":,
{"learn":[0.1958710124],"iteration":81,"passed_time":0.4511537196,"remaining_time":5,
{"learn",
{"learn":[0.1945578216],"iteration":82,"passed_time":0.4568941719,"remaining_time":5,
{"learn":,
{"learn":[0.1933576336],"iteration":83,"passed_time":0.4613424585,"remaining_time":5,
{"learn":,
{"learn":[0.1920575899],"iteration":84,"passed_time":0.466938968,"remaining_time":5.,
{"learn",
{"learn":[0.1908391721],"iteration":85,"passed_time":0.471861697,"remaining_time":5.,
{"learn":[0.1900533407],"iteration":86,"passed_time":0.4790562474,"remaining_time":5.0273374},
{"learn":[0.188878179],"iteration":87,"passed_time":0.4846988733,"remaining_time":5.023242869},
{"learn":[0.1876282394],"iteration":88,"passed_time":0.4904337049,"remaining_time":5.020057361},
{"learn":[0.1866772069],"iteration":89,"passed_time":0.495141637,"remaining_time":5.006432108},
{"learn":[0.185925239],"iteration":90,"passed_time":0.5006380786,"remaining_time":5.000879268},
{"learn":[0.1846474017],"iteration":91,"passed_time":0.5059004713,"remaining_time":4.993017695},
{"learn":[0.1835144311],"iteration":92,"passed_time":0.5118092833,"remaining_time":4.991516344},
{"learn":[0.1826666135],"iteration":93,"passed_time":0.5175254821,"remaining_time":4.988064753},
{"learn":[0.1816635162],"iteration":94,"passed_time":0.5235348738,"remaining_time":4.987358535},
{"learn":[0.1805954585],"iteration":95,"passed_time":0.528733549,"remaining_time":4.978907587},
{"learn":[0.1797027841],"iteration":96,"passed_time":0.5347842008,"remaining_time":4.978454982},
{"learn",
{"learn":[0.1788778941],"iteration":97,"passed_time":0.5380200201,"remaining_time":4.,
{"learn":[0.1779682252],"iteration":98,"passed_time":0.5453305413,"remaining_time":4.963058764},
{"learn,
{"learn":[0.1772186773],"iteration":99,"passed_time":0.5480848633,"remaining_time":4.9,
{"learn":[0.1763158493],"iteration":100,"passed_time":0.5556496593,"remaining_time":4.945832116},
{"lear,
{"learn":[0.175657363],"iteration":101,"passed_time":0.5587136075,"remaining_time":4.918,
{"le,
{"learn":[0.1748630386],"iteration":102,"passed_time":0.5643620753,"remaining_time":4.9148,
{"le,
{"learn":[0.1741099819],"iteration":103,"passed_time":0.5698510668,"remaining_time":4.90,
{"lear,
{"learn":[0.1736077463],"iteration":104,"passed_time":0.5748583572,"remaining_time":4.89,
{"lea,
{"learn":[0.172898354],"iteration":105,"passed_time":0.5799749251,"remaining_time":4.89,
{"lear,
{"learn":[0.1720530117],"iteration":106,"passed_time":0.5856822307,"remaining_time":4.88,
{"lear,
{"learn":[0.1711781237],"iteration":107,"passed_time":0.5924999782,"remaining_time":4.89,
{"lear,
{"learn":[0.1704788044],"iteration":108,"passed_time":0.5981073,"remaining_time":4.88911,
{"l,
{"learn":[0.1696543216],"iteration":109,"passed_time":0.6045913654,"remaining_time":4.89169,
{"l,
{"learn":[0.1688593972],"iteration":110,"passed_time":0.610547586,"remaining_time":4.88988,
{"l,
{"learn":[0.1682363153],"iteration":111,"passed_time":0.6152528965,"remaining_time":4.87807,
{"l,
{"learn":[0.1673549982],"iteration":112,"passed_time":0.6214667372,"remaining_time":4.87823,
{"l,
{"learn":[0.1666103077],"iteration":113,"passed_time":0.6264488635,"remaining_time":4.8687,
{"le,
{"learn":[0.1656721359],"iteration":114,"passed_time":0.6315950666,"remaining_time":4.8605,
{"le,
{"learn":[0.1649760703],"iteration":115,"passed_time":0.6369492994,"remaining_time":4.853,
{"lea,
{"learn":[0.1645706393],"iteration":116,"passed_time":0.6428180597,"remaining_time":4.851353391},
{"learn":[0.1637579912],"iteration":117,"passed_time":0.6475495317,"remaining_time":4.8,
{"learn,
{"learn":[0.1632365978],"iteration":118,"passed_time":0.6526244082,"remaining_time":4.8,
{"learn,
{"learn":[0.1624543687],"iteration":119,"passed_time":0.6569652487,"remaining_time":4.8,
{"learn,
{"learn":[0.161710712],"iteration":120,"passed_time":0.6624463878,"remaining_time":4.8,
{"learn,
{"learn":[0.1608478358],"iteration":121,"passed_time":0.6668866341,"remaining_time":4.7,
{"learn,
{"learn":[0.160350015],"iteration":122,"passed_time":0.6728126095,"remaining_time":4.79,
{"lear,
{"learn":[0.1596493768],"iteration":123,"passed_time":0.6780482945,"remaining_time":4.79,
{"lear,
{"learn":[0.1592718749],"iteration":124,"passed_time":0.6825126992,"remaining_time":4.77,
{"lear,
{"learn":[0.1587630679],"iteration":125,"passed_time":0.6878790519,"remaining_time":4.77,
{"lear,
{"learn":[0.1581602372],"iteration":126,"passed_time":0.6938370992,"remaining_time":4.76,
{"lear,
{"learn":[0.1576791226],"iteration":127,"passed_time":0.6986788846,"remaining_time":4.7,
{"learn,
{"learn":[0.1572212634],"iteration":128,"passed_time":0.7038466207,"remaining_time":4.7,
{"learn,
{"learn":[0.1567452365],"iteration":129,"passed_time":0.7098362832,"remaining_time":4.,
{"learn",
{"learn":[0.1561216428],"iteration":130,"passed_time":0.7152870044,"remaining_time":4.,
{"learn",
{"learn":[0.1556749019],"iteration":131,"passed_time":0.7211399508,"remaining_time":4,
{"learn":,
{"learn":[0.154938409],"iteration":132,"passed_time":0.7265558411,"remaining_time":4.,
{"learn",
{"learn":[0.1545160973],"iteration":133,"passed_time":0.7312382371,"remaining_time":4,
{"learn":,
{"learn":[0.1539744321],"iteration":134,"passed_time":0.7375538751,"remaining_time":4,
{"learn":,
{"learn":[0.1532287116],"iteration":135,"passed_time":0.7426758458,"remaining_time":,
{"learn":[,
{"learn":[0.1527267525],"iteration":136,"passed_time":0.7477685917,"remaining_time":,
{"learn":[,
{"learn":[0.1522179947],"iteration":137,"passed_time":0.7529808989,"remaining_time",
{"learn":[0,
{"learn":[0.1516662687],"iteration":138,"passed_time":0.7589975291,"remaining_time",
{"learn":[0,
{"learn":[0.1512369506],"iteration":139,"passed_time":0.7636995546,"remaining_time",
{"learn":[0,
{"learn":[0.1506216917],"iteration":140,"passed_time":0.7689975437,"remaining_time",
{"learn":[0,
{"learn":[0.1501515179],"iteration":141,"passed_time":0.7738490708,"remaining_time",
{"learn":[0,
{"learn":[0.1495926935],"iteration":142,"passed_time":0.7794920346,"remaining_time",
{"learn":[0,
{"learn":[0.1490359521],"iteration":143,"passed_time":0.7851639588,"remaining_time",
{"learn":[0,
{"learn":[0.1487858972],"iteration":144,"passed_time":0.790084454,"remaining_time":,
{"learn":[,
{"learn":[0.1483357052],"iteration":145,"passed_time":0.7951360523,"remaining_time":,
{"learn":[,
{"learn":[0.1479084885],"iteration":146,"passed_time":0.8000297834,"remaining_time":,
{"learn":[,
{"learn":[0.1475030475],"iteration":147,"passed_time":0.8049469675,"remaining_time",
{"learn":[0,
{"learn":[0.1471026961],"iteration":148,"passed_time":0.8107738547,"remaining_time",
{"learn":[0,
{"learn":[0.1464450533],"iteration":149,"passed_time":0.8171714651,"remaining_time",
{"learn":[0,
{"learn":[0.1459804638],"iteration":150,"passed_time":0.8221794663,"remaining_time",
{"learn":[0,
{"learn":[0.1454001484],"iteration":151,"passed_time":0.8278438087,"remaining_time",
{"learn":[0,
{"learn":[0.1449801731],"iteration":152,"passed_time":0.8326434344,"remaining_time",
{"learn":[0,
{"learn":[0.1446768774],"iteration":153,"passed_time":0.8374940664,"remaining_time",
{"learn":[0,
{"learn":[0.1439610223],"iteration":154,"passed_time":0.8434767027,"remaining_time",
{"learn":[0,
{"learn":[0.1437023847],"iteration":155,"passed_time":0.8488234385,"remaining_time",
{"learn":[0,
{"learn":[0.1431074223],"iteration":156,"passed_time":0.8542078845,"remaining_time",
{"learn":[0,
{"learn":[0.1428260514],"iteration":157,"passed_time":0.8591910123,"remaining_time",
{"learn":[0,
{"learn":[0.1422906545],"iteration":158,"passed_time":0.8640952447,"remaining_time",
{"learn":[0,
{"learn":[0.1418792818],"iteration":159,"passed_time":0.8704224269,"remaining_time,
{"learn":[0.,
{"learn":[0.1412327856],"iteration":160,"passed_time":0.8760730883,"remaining_time,
{"learn":[0.,
{"learn":[0.1407109429],"iteration":161,"passed_time":0.8821846303,"remaining_time,
{"learn":[0.,
{"learn":[0.1403537771],"iteration":162,"passed_time":0.888236148,"remaining_time",
{"learn":[0,
{"learn":[0.1397913567],"iteration":163,"passed_time":0.8942172185,"remaining_time",
{"learn":[0,
{"learn":[0.1394098425],"iteration":164,"passed_time":0.8998280702,"remaining_time",
{"learn":[0,
{"learn":[0.1388521793],"iteration":165,"passed_time":0.9045942842,"remaining_time",
{"learn":[0,
{"learn":[0.1384095752],"iteration":166,"passed_time":0.9096316876,"remaining_time",
{"learn":[0,
{"learn":[0.1379836627],"iteration":167,"passed_time":0.9158057316,"remaining_time,
{"learn":[0.,
{"learn":[0.1377330531],"iteration":168,"passed_time":0.9206050518,"remaining_time,
{"learn":[0.,
{"learn":[0.1374540142],"iteration":169,"passed_time":0.9256415549,"remaining_time,
{"learn":[0.,
{"learn":[0.1371798108],"iteration":170,"passed_time":0.9319040142,"remaining_time":4.517827063},
{"learn":[0.1368504935],"iteration":171,"passed_time":0.9376923069,"remaining_time":4.514007152},
{"learn":[0.1364484139],"iteration":172,"passed_time":0.9435824301,"remaining_time":4.51065127},
{"learn":[0.1360388661],"iteration":173,"passed_time":0.9487636439,"remaining_time":4.503900976},
{"learn":[0.135784592],"iteration":174,"passed_time":0.9547915786,"remaining_time":4.501160299},
{"learn":[0.1355125388],"iteration":175,"passed_time":0.9600156867,"remaining_time":4.494618897},
{"learn":[0.135182784],"iteration":176,"passed_time":0.9649585221,"remaining_time":4.486784541},
{"learn":[0.1348307979],"iteration":177,"passed_time":0.9706106195,"remaining_time":4.482258029},
{"learn":[0.1344434978],"iteration":178,"passed_time":0.9760953346,"remaining_time":4.476951227},
{"learn":[0.1339816414],"iteration":179,"passed_time":0.9810976253,"remaining_time":4.469444737},
{"learn":[0.1336572212],"iteration":180,"passed_time":0.9858288543,"remaining_time":4.460739401},
{"learn":[0.1331819616],"iteration":181,"passed_time":0.9909712819,"remaining_tim,
{"learn":[0.1,
{"learn":[0.1324583845],"iteration":182,"passed_time":0.9964629361,"remaining_tim,
{"learn":[0.,
{"learn":[0.1320936098],"iteration":183,"passed_time":1.000838604,"remaining_time,
{"learn":[0.,
{"learn":[0.1319216057],"iteration":184,"passed_time":1.006564639,"remaining_ti,
{"learn":[0.13,
{"learn":[0.1315426317],"iteration":185,"passed_time":1.011412726,"remaining_t,
{"learn":[0.130,
{"learn":[0.1312489592],"iteration":186,"passed_time":1.016719866,"remaining_,
{"learn":[0.1299,
{"learn":[0.1310176669],"iteration":187,"passed_time":1.02249527,"remaining_t,
{"learn":[0.129,
{"learn":[0.130837531],"iteration":188,"passed_time":1.028455654,"remaining_ti,
{"learn":[0.12,
{"learn":[0.1301900002],"iteration":189,"passed_time":1.033411673,"remaining_t,
{"learn":[0.128,
{"learn":[0.1300813904],"iteration":190,"passed_time":1.037570889,"remaining_t,
{"learn":[0.128,
{"learn":[0.1299555436],"iteration":191,"passed_time":1.042453353,"remaining_t,
{"learn":[0.128,
{"learn":[0.1295327275],"iteration":192,"passed_time":1.047554472,"remaining_t,
{"learn":[0.127,
{"learn":[0.1290481315],"iteration":193,"passed_time":1.053201154,"remaining_t,
{"learn":[0.127,
{"learn":[0.1287008965],"iteration":194,"passed_time":1.058268738,"remaining_t,
{"learn":[0.127,
{"learn":[0.1283413177],"iteration":195,"passed_time":1.06361627,"remaining_ti,
{"learn":[0.12,
{"learn":[0.1279083361],"iteration":196,"passed_time":1.070157346,"remaining_,
{"learn":[0.1265,
{"learn":[0.1277224715],"iteration":197,"passed_time":1.074525421,"remaining,
{"learn":[0.12617,
{"learn":[0.1271073723],"iteration":198,"passed_time":1.081240799,"remaining,
{"learn":[0.1258,
{"learn":[0.1266169714],"iteration":199,"passed_time":1.087315554,"remaining_,
{"learn":[0.1252,
{"learn":[0.1261932597],"iteration":200,"passed_time":1.091636297,"remaining,
{"learn":[0.12499,
{"learn":[0.1258557716],"iteration":201,"passed_time":1.096537527,"remaining,
{"learn":[0.1246,
{"learn":[0.1255859905],"iteration":202,"passed_time":1.101574499,"remaining_,
{"learn":[0.1241,
{"learn":[0.1254084419],"iteration":203,"passed_time":1.10615806,"remaining_t,
{"learn":[0.123,
{"learn":[0.125056467],"iteration":204,"passed_time":1.112281369,"remaining_ti,
{"learn":[0.12,
{"learn":[0.1246851981],"iteration":205,"passed_time":1.117105708,"remaining_t,
{"learn":[0.122,
{"learn":[0.1242662287],"iteration":206,"passed_time":1.12299098,"remaining_ti,
{"learn":[0.1,
{"learn":[0.123958552],"iteration":207,"passed_time":1.129021712,"remaining_ti,
{"learn":[0.12,
{"learn":[0.123683208],"iteration":208,"passed_time":1.134411326,"remaining_tim,
{"learn":[0.,
{"learn":[0.1232498255],"iteration":209,"passed_time":1.139501403,"remaining_time,
{"learn":[0.,
{"learn":[0.1229660249],"iteration":210,"passed_time":1.145528677,"remaining_time,
{"learn":[0.,
{"learn":[0.1226879606],"iteration":211,"passed_time":1.151508504,"remaining_time,
{"learn":[0.,
{"learn":[0.1224486367],"iteration":212,"passed_time":1.155745984,"remaining_tim,
{"learn":[0.1,
{"learn":[0.1219977351],"iteration":213,"passed_time":1.162144613,"remaining_tim,
{"learn":[0.,
{"learn":[0.1218825108],"iteration":214,"passed_time":1.166960406,"remaining_time,
{"learn":[0.,
{"learn":[0.1213554085],"iteration":215,"passed_time":1.171580212,"remaining_time,
{"learn":[0.,
{"learn":[0.1210199384],"iteration":216,"passed_time":1.177909948,"remaining_time,
{"learn":[0.,
{"learn":[0.1206321044],"iteration":217,"passed_time":1.183348602,"remaining_time,
{"learn":[0.,
{"learn":[0.120542227],"iteration":218,"passed_time":1.187953161,"remaining_time",
{"learn":[0,
{"learn":[0.1199210634],"iteration":219,"passed_time":1.194260855,"remaining_time",
{"learn":[0,
{"learn":[0.1193809933],"iteration":220,"passed_time":1.201107659,"remaining_time,
{"learn":[0.,
{"learn":[0.1189730784],"iteration":221,"passed_time":1.206599792,"remaining_tim,
{"learn":[0.1,
{"learn":[0.1185943585],"iteration":222,"passed_time":1.212364012,"remaining_tim,
{"learn":[0.1,
{"learn":[0.1185028579],"iteration":223,"passed_time":1.218286324,"remaining_tim,
{"learn":[0.,
{"learn":[0.1181730516],"iteration":224,"passed_time":1.224745482,"remaining_time,
{"learn":[0.,
{"learn":[0.1178284227],"iteration":225,"passed_time":1.23002197,"remaining_time,
{"learn":[0.,
{"learn":[0.1173851331],"iteration":226,"passed_time":1.23558855,"remaining_time",
{"learn":[0,
{"learn":[0.1170106013],"iteration":227,"passed_time":1.24134197,"remaining_time",
{"learn":[0,
{"learn":[0.1167648138],"iteration":228,"passed_time":1.247447531,"remaining_time",
{"learn":,
{"learn":[0.1164724942],"iteration":229,"passed_time":1.253820722,"remaining_time":4,
{"learn":,
{"learn":[0.1162093872],"iteration":230,"passed_time":1.260089547,"remaining_time":4,
{"learn":,
{"learn":[0.1159397499],"iteration":231,"passed_time":1.266170358,"remaining_time":4,
{"learn":,
{"learn":[0.1154166737],"iteration":232,"passed_time":1.271796402,"remaining_time":,
{"learn":[,
{"learn":[0.1152789835],"iteration":233,"passed_time":1.277810865,"remaining_time":,
{"learn":[,
{"learn":[0.1151868326],"iteration":234,"passed_time":1.283533643,"remaining_time",
{"learn":[0,
{"learn":[0.1149880832],"iteration":235,"passed_time":1.28933936,"remaining_time":,
{"learn":[,
{"learn":[0.1145624121],"iteration":236,"passed_time":1.29548504,"remaining_time":4,
{"learn":,
{"learn":[0.1141102968],"iteration":237,"passed_time":1.301663462,"remaining_time":,
{"learn":[,
{"learn":[0.1138340125],"iteration":238,"passed_time":1.308545705,"remaining_time":,
{"learn":[,
{"learn":[0.1137064129],"iteration":239,"passed_time":1.313099874,"remaining_time":,
{"learn":[,
{"learn":[0.113601521],"iteration":240,"passed_time":1.319858635,"remaining_time":4,
{"learn":,
{"learn":[0.1135305682],"iteration":241,"passed_time":1.326686913,"remaining_time":4,
{"learn":,
{"learn":[0.1133147351],"iteration":242,"passed_time":1.331959016,"remaining_time":4.149353807},
{"learn":[0.1130323437],"iteration":243,"passed_time":1.337585381,"remaining_time":4.144321917},
{"learn":[0.1128877963],"iteration":244,"passed_time":1.343144269,"remaining_time":4.139077238},
{"learn":[0.1128188886],"iteration":245,"passed_time":1.349410146,"remaining_time":4.135996952},
{"learn":[0.112426397],"iteration":246,"passed_time":1.356000133,"remaining_time":4.133878947},
{"learn":[0.1121125617],"iteration":247,"passed_time":1.361890227,"remaining_time":4.129602623},
{"learn":[0.111919066],"iteration":248,"passed_time":1.367614838,"remaining_time":4.124814229},
{"learn":[0.1118036186],"iteration":249,"passed_time":1.372866786,"remaining_time":4.118600359},
{"learn":[0.1114761471],"iteration":250,"passed_time":1.377743392,"remaining_time":4.111274107},
{"learn":[0.1112219042],"iteration":251,"passed_time":1.383427201,"remaining_time":4.10636328},
{"learn":[0.1108881144],"iteration":252,"passed_time":1.390100825,"remaining_time":4.10436884},
{"learn":[0.1107181349],"iteration":253,"passed_time":1.39518791,"remaining_time":4.097677878},
{"learn":[0.110296463],"iteration":254,"passed_time":1.400059532,"remaining_time":4.090370005},
{"learn":[0.1101736201],"iteration":255,"passed_time":1.406910897,"remaining_time":4.088834794},
{"learn":[0.110012381],"iteration":256,"passed_time":1.414296195,"remaining_time":4.088801839},
{"learn":[0.1098126449],"iteration":257,"passed_time":1.419881755,"remaining_time":4.083535901},
{"learn":[0.1094309541],"iteration":258,"passed_time":1.424190402,"remaining_time":4.07461424},
{"learn":[0.1093144907],"iteration":259,"passed_time":1.430220524,"remaining_time":4.070627645},
{"learn":[0.1089849936],"iteration":260,"passed_time":1.435551604,"remaining_time":4.064646112},
{"learn":[0.1089201993],"iteration":261,"passed_time":1.440863796,"remaining_time":4.058616342},
{"learn":[0.1088232794],"iteration":262,"passed_time":1.446944039,"remaining_time":4.054744321},
{"learn":[0.1087312926],"iteration":263,"passed_time":1.450926377,"remaining_time":4.045006869},
{"learn":[0.1083075633],"iteration":264,"passed_time":1.456271397,"remaining_time":4.039092365},
{"learn":[0.10807291],"iteration":265,"passed_time":1.461676331,"remaining_time":4.03334747},
{"learn":[0.1077234558],"iteration":266,"passed_time":1.466555796,"remaining_time":4.0,
{"learn,
{"learn":[0.1076706409],"iteration":267,"passed_time":1.472119927,"remaining_time":4.,
{"learn",
{"learn":[0.1071698029],"iteration":268,"passed_time":1.478755113,"remaining_time":4.,
{"learn,
{"learn":[0.1066742739],"iteration":269,"passed_time":1.485920278,"remaining_time":4.01748816},
{"learn":[0.1063597458],"iteration":270,"passed_time":1.491853677,"remaining_time":4.01314144},
{"learn":[0.106130085],"iteration":271,"passed_time":1.497813223,"remaining_time":4.008853039},
{"learn":[0.1058501868],"iteration":272,"passed_time":1.503336379,"remaining_time":4.003390285},
{"learn":[0.1057894283],"iteration":273,"passed_time":1.509480927,"remaining_time":3.99957355},
{"learn":[0.1054077005],"iteration":274,"passed_time":1.515071949,"remaining_time":3.994280594},
{"learn":[0.1050395442],"iteration":275,"passed_time":1.520697292,"remaining_time":3.9890,
{"le,
{"learn":[0.1049940992],"iteration":276,"passed_time":1.527351406,"remaining_time":3.986552587},
{"learn":[0.1046215152],"iteration":277,"passed_time":1.532811486,"remaining_time":3.980898895},
{"learn":[0.1045456208],"iteration":278,"passed_time":1.538833272,"remaining_time":3.976698169},
{"learn":[0.1044044106],"iteration":279,"passed_time":1.54503877,"remaining_time":3.972956837},
{"learn":[0.1040396242],"iteration":280,"passed_time":1.550682222,"remaining_time":3.96775985},
{"learn":[0.1039193966],"iteration":281,"passed_time":1.556865344,"remaining_time":3.963933748},
{"learn":[0.1037336835],"iteration":282,"passed_time":1.56252287,"remaining_time":3.958759356},
{"learn":[0.1033864141],"iteration":283,"passed_time":1.569597018,"remaining_time":3.957153045},
{"learn":[0.1030451288],"iteration":284,"passed_time":1.574048802,"remaining_time":3.948929451},
{"learn":[0.1029608719],"iteration":285,"passed_time":1.579759932,"remaining_time":3.943876195},
{"learn":[0.1026091697],"iteration":286,"passed_time":1.585481413,"remaining_time":3.938844068},
{"learn":[0.1022107205],"iteration":287,"passed_time":1.590975183,"remaining_time":3.933244202},
{"learn":[0.1019469507],"iteration":288,"passed_time":1.597314138,"remaining_time":3.929724401},
{"learn":[0.101701237],"iteration":289,"passed_time":1.603184813,"remaining_time":3.925038679},
{"learn":[0.1016206838],"iteration":290,"passed_time":1.608879137,"remaining_time":3.919915147},
{"learn":[0.1013032054],"iteration":291,"passed_time":1.613444566,"remaining_time":3.912050522},
{"learn":[0.1011986142],"iteration":292,"passed_time":1.618856479,"remaining_time":3.906250957},
{"learn":[0.1008914131],"iteration":293,"passed_time":1.623069847,"remaining_time":3.897575891},
{"learn":[0.1008504604],"iteration":294,"passed_time":1.628667033,"remaining_time":3.892238164},
{"learn":[0.1007711146],"iteration":295,"passed_time":1.634024302,"remaining_time":3.886328069},
{"learn":[0.1003220007],"iteration":296,"passed_time":1.638542536,"remaining_time":3.8784357},
{"learn":[0.1002823289],"iteration":297,"passed_time":1.644139252,"remaining_time":3.87310656},
{"learn":[0.1000896322],"iteration":298,"passed_time":1.649710934,"remaining_time":3.867716939},
{"learn":[0.09980926207],"iteration":299,"passed_time":1.656231597,"remaining_time":3.864540392},
{"learn":[0.09945896683],"iteration":300,"passed_time":1.663474389,"remaining_time":3.863018597},
{"learn":[0.09895951031],"iteration":301,"passed_time":1.66978591,"remaining_time":3.859306507},
{"learn":[0.0988795732],"iteration":302,"passed_time":1.67475706,"remaining_time":3.852493963},
{"learn":[0.09847172472],"iteration":303,"passed_time":1.68212255,"remaining_time":3.851175313},
{"learn":[0.09835190156],"iteration":304,"passed_time":1.689657725,"remaining_time":3.850203668},
{"learn":[0.09811339421],"iteration":305,"passed_time":1.697402966,"remaining_time":3.84966555},
{"learn":[0.09807096818],"iteration":306,"passed_time":1.703337497,"remaining_time":3.844993113},
{"learn":[0.09798569833],"iteration":307,"passed_time":1.712755424,"remaining_time":3.84813881},
{"learn":[0.09786700141],"iteration":308,"passed_time":1.723432274,"remaining_time":3.854018451},
{"learn":[0.09782374594],"iteration":309,"passed_time":1.730206249,"remaining_time":3.851104232},
{"learn":[0.09772204199],"iteration":310,"passed_time":1.739520851,"remaining_time":3.853793783},
{"learn":[0.09758150963],"iteration":311,"passed_time":1.747596124,"remaining_time":3.853673505},
{"learn":[0.09732418576],"iteration":312,"passed_time":1.774585283,"remaining_time":3.895016259},
{"learn":[0.0972868197],"iteration":313,"passed_time":1.791353325,"remaining_time":3.91359357},
{"learn":[0.09725270399],"iteration":314,"passed_time":1.797389516,"remaining_time":3.908608948},
{"learn":[0.0972197062],"iteration":315,"passed_time":1.803255598,"remaining_time":3.903249459},
{"learn":[0.09683654236],"iteration":316,"passed_time":1.810911081,"remaining_time":3.901742171},
{"learn":[0.09662347812],"iteration":317,"passed_time":1.817062721,"remaining_time":3.896970993},
{"learn":[0.09629922174],"iteration":318,"passed_time":1.825372038,"remaining_time":3.896797359},
{"learn":[0.09605829281],"iteration":319,"passed_time":1.834147697,"remaining_time":3.897563856},
{"learn":[0.09601520157],"iteration":320,"passed_time":1.840078954,"remaining_time":3.892254236},
{"learn":[0.09575724958],"iteration":321,"passed_time":1.847364091,"remaining_time":3.889791471},
{"learn":[0.09530692818],"iteration":322,"passed_time":1.854115649,"remaining_time":3.886180478},
{"learn":[0.09498035152],"iteration":323,"passed_time":1.859796548,"remaining_time":3.880316255},
{"learn":[0.09465685604],"iteration":324,"passed_time":1.86611499,"remaining_time":3.875777287},
{"learn":[0.09430518007],"iteration":325,"passed_time":1.872284855,"remaining_time":3.870920221},
{"learn":[0.09427819282],"iteration":326,"passed_time":1.878827699,"remaining_time":3.866822756},
{"learn":[0.09401242794],"iteration":327,"passed_time":1.884404172,"remaining_time":3.8607305},
{"learn":[0.09374550129],"iteration":328,"passed_time":1.890264946,"remaining_time":3.855221211},
{"learn":[0.09340647859],"iteration":329,"passed_time":1.896011163,"remaining_time":3.849477209},
{"learn":[0.0933767541],"iteration":330,"passed_time":1.901444687,"remaining_time":3.843101196},
{"learn":[0.09306261149],"iteration":331,"passed_time":1.908152824,"remaining_time":3.839295441},
{"learn":[0.09275808213],"iteration":332,"passed_time":1.914200327,"remaining_time":3.834149003},
{"learn":[0.09245564321],"iteration":333,"passed_time":1.920849153,"remaining_time":3.830196214},
{"learn":[0.09235849927],"iteration":334,"passed_time":1.92700556,"remaining_time":3.825249844},
{"learn":[0.09227333866],"iteration":335,"passed_time":1.932972194,"remaining_time":3.819921241},
{"learn":[0.09218100784],"iteration":336,"passed_time":1.939742288,"remaining_time":3.816169545},
{"learn":[0.09186670778],"iteration":337,"passed_time":1.946502856,"remaining_time":3.812381333},
{"learn":[0.09163230377],"iteration":338,"passed_time":1.9515904,"remaining_time":3.805313436},
{"learn":[0.09158929492],"iteration":339,"passed_time":1.961462863,"remaining_time":3.807545558},
{"learn":[0.09155008313],"iteration":340,"passed_time":1.96611954,"remaining_time":3.799626912},
{"learn":[0.09152001696],"iteration":341,"passed_time":1.97199837,"remaining_time":3.794078734},
{"learn":[0.09144928443],"iteration":342,"passed_time":1.978146446,"remaining_time":3.789044359},
{"learn":[0.09109729538],"iteration":343,"passed_time":1.982749341,"remaining_time":3.781056883},
{"learn":[0.09105902264],"iteration":344,"passed_time":1.988987129,"remaining_time":3.776192954},
{"learn":[0.09074713237],"iteration":345,"passed_time":1.995528305,"remaining_time":3.771894542},
{"learn":[0.09043157602],"iteration":346,"passed_time":2.001616908,"remaining_time":3.76673153},
{"learn":[0.09035539911],"iteration":347,"passed_time":2.006506664,"remaining_time":3.759317084},
{"learn":[0.0900696219],"iteration":348,"passed_time":2.011468503,"remaining_time":3.752051563},
{"learn":[0.08983503909],"iteration":349,"passed_time":2.015762145,"remaining_time":3.743558269},
{"learn":[0.08952575703],"iteration":350,"passed_time":2.021466306,"remaining_time":3.737696958},
{"learn":[0.08948522864],"iteration":351,"passed_time":2.027302022,"remaining_time":3.732078723},
{"learn":[0.08944696012],"iteration":352,"passed_time":2.032451315,"remaining_time":3.725201135},
{"learn":[0.08929571631],"iteration":353,"passed_time":2.037217793,"remaining_time":3.717634729},
{"learn":[0.0892607769],"iteration":354,"passed_time":2.042314844,"remaining_time":3.710684717},
{"learn":[0.08923774903],"iteration":355,"passed_time":2.047752847,"remaining_time":3.704361893},
{"learn":[0.0891290466],"iteration":356,"passed_time":2.052640965,"remaining_time":3.697053615},
{"learn":[0.08907055939],"iteration":357,"passed_time":2.058573513,"remaining_time":3.691631831},
{"learn":[0.08894828774],"iteration":358,"passed_time":2.063948888,"remaining_time":3.685212359},
{"learn":[0.08878028022],"iteration":359,"passed_time":2.069640323,"remaining_time":3.679360575},
{"learn":[0.08867671504],"iteration":360,"passed_time":2.074600972,"remaining_time":3.672216125},
{"learn":[0.0886325851],"iteration":361,"passed_time":2.080065028,"remaining_time":3.665970961},
{"learn":[0.0884688653],"iteration":362,"passed_time":2.085586337,"remaining_time":3.659830569},
{"learn":[0.08843817726],"iteration":363,"passed_time":2.091674565,"remaining_time":3.65468413},
{"learn":[0.08842027035],"iteration":364,"passed_time":2.096709756,"remaining_time":3.647700534},
{"learn":[0.08831023857],"iteration":365,"passed_time":2.104566614,"remaining_time":3.645615392},
{"learn":[0.08828474953],"iteration":366,"passed_time":2.110672003,"remaining_time":3.640477868},
{"learn":[0.08825438268],"iteration":367,"passed_time":2.116202589,"remaining_time":3.634347925},
{"learn":[0.08801863624],"iteration":368,"passed_time":2.121202326,"remaining_time":3.627313462},
{"learn":[0.08770118818],"iteration":369,"passed_time":2.126819771,"remaining_time":3.621341773},
{"learn":[0.08735454072],"iteration":370,"passed_time":2.131698155,"remaining_time":3.614118974},
{"learn":[0.08717281087],"iteration":371,"passed_time":2.136809533,"remaining_time":3.607302114},
{"learn":[0.08701516037],"iteration":372,"passed_time":2.142473978,"remaining_time":3.601424087},
{"learn":[0.08697332883],"iteration":373,"passed_time":2.147171558,"remaining_time":3.593928864},
{"learn":[0.08665334389],"iteration":374,"passed_time":2.152521524,"remaining_time":3.587535873},
{"learn":[0.08660351407],"iteration":375,"passed_time":2.158417101,"remaining_time":3.582053911},
{"learn":[0.08642368229],"iteration":376,"passed_time":2.162545177,"remaining_time":3.573648926},
{"learn":[0.08615199632],"iteration":377,"passed_time":2.167200843,"remaining_time":3.56613472},
{"learn":[0.08590894133],"iteration":378,"passed_time":2.173701092,"remaining_time":3.561657989},
{"learn":[0.08570989607],"iteration":379,"passed_time":2.178657166,"remaining_time":3.554651166},
{"learn":[0.08569165371],"iteration":380,"passed_time":2.183731611,"remaining_time":3.54784742},
{"learn":[0.08540929608],"iteration":381,"passed_time":2.189672676,"remaining_time":3.542454748},
{"learn":[0.08521905767],"iteration":382,"passed_time":2.194235194,"remaining_time":3.534838419},
{"learn":[0.08517540578],"iteration":383,"passed_time":2.199747699,"remaining_time":3.528761933},
{"learn":[0.08509737253],"iteration":384,"passed_time":2.20542164,"remaining_time":3.522946256},
{"learn":[0.0848472835],"iteration":385,"passed_time":2.211084033,"remaining_time":3.517112943},
{"learn":[0.084513421],"iteration":386,"passed_time":2.217319964,"remaining_time":3.512188987},
{"learn":[0.08429191227],"iteration":387,"passed_time":2.221860631,"remaining_time":3.504584295},
{"learn":[0.08401825941],"iteration":388,"passed_time":2.22729423,"remaining_time":3.498397879},
{"learn":[0.08393265486],"iteration":389,"passed_time":2.232952798,"remaining_time":3.492567196},
{"learn":[0.08383562704],"iteration":390,"passed_time":2.239054702,"remaining_time":3.487427911},
{"learn":[0.08380831331],"iteration":391,"passed_time":2.245612278,"remaining_time":3.482990472},
{"learn":[0.08364315381],"iteration":392,"passed_time":2.251521233,"remaining_time":3.477540429},
{"learn":[0.08359547871],"iteration":393,"passed_time":2.256044411,"remaining_time":3.469956632},
{"learn":[0.08339961288],"iteration":394,"passed_time":2.260995123,"remaining_time":3.463043163},
{"learn":[0.08304578324],"iteration":395,"passed_time":2.265939283,"remaining_time":3.456129614},
{"learn":[0.08285919239],"iteration":396,"passed_time":2.271191619,"remaining_time":3.449694071},
{"learn":[0.08269351971],"iteration":397,"passed_time":2.275975617,"remaining_time":3.442556084},
{"learn":[0.08253901321],"iteration":398,"passed_time":2.282522222,"remaining_time":3.438084851},
{"learn":[0.08227114323],"iteration":399,"passed_time":2.287818885,"remaining_time":3.431728328},
{"learn":[0.08198903634],"iteration":400,"passed_time":2.291993111,"remaining_time":3.423700433},
{"learn":[0.08185299109],"iteration":401,"passed_time":2.298184011,"remaining_time":3.418691638},
{"learn":[0.08170372886],"iteration":402,"passed_time":2.303761071,"remaining_time":3.412767641},
{"learn":[0.08166586434],"iteration":403,"passed_time":2.309091393,"remaining_time":3.406481362},
{"learn":[0.08157630583],"iteration":404,"passed_time":2.314998516,"remaining_time":3.401047203},
{"learn":[0.08134019316],"iteration":405,"passed_time":2.321426115,"remaining_time":3.396372198},
{"learn":[0.08116727705],"iteration":406,"passed_time":2.32606459,"remaining_time":3.389081822},
{"learn":[0.08093403436],"iteration":407,"passed_time":2.332089072,"remaining_time":3.383815516},
{"learn":[0.08075239551],"iteration":408,"passed_time":2.339083125,"remaining_time":3.379946521},
{"learn":[0.08055657343],"iteration":409,"passed_time":2.344611716,"remaining_time":3.373953445},
{"learn":[0.08044536168],"iteration":410,"passed_time":2.349905146,"remaining_time":3.367625622},
{"learn":[0.08026862085],"iteration":411,"passed_time":2.354837261,"remaining_time":3.360787159},
{"learn":[0.08012019613],"iteration":412,"passed_time":2.359929634,"remaining_time":3.354185702},
{"learn":[0.07990706168],"iteration":413,"passed_time":2.365468726,"remaining_time":3.348223849},
{"learn":[0.07972716436],"iteration":414,"passed_time":2.371981884,"remaining_time":3.343637113},
{"learn":[0.07940721063],"iteration":415,"passed_time":2.378576853,"remaining_time":3.339155966},
{"learn":[0.07926922528],"iteration":416,"passed_time":2.384264249,"remaining_time":3.33339582},
{"learn":[0.07916847263],"iteration":417,"passed_time":2.390125666,"remaining_time":3.32787832},
{"learn":[0.07899574812],"iteration":418,"passed_time":2.396451411,"remaining_time":3.32300303},
{"learn":[0.07872026635],"iteration":419,"passed_time":2.401628304,"remaining_time":3.316534325},
{"learn":[0.07848010855],"iteration":420,"passed_time":2.406853265,"remaining_time":3.310137864},
{"learn":[0.07838680582],"iteration":421,"passed_time":2.412537552,"remaining_time":3.304376078},
{"learn":[0.07830705896],"iteration":422,"passed_time":2.418815414,"remaining_time":3.299424336},
{"learn":[0.07826718051],"iteration":423,"passed_time":2.423988628,"remaining_time":3.292965683},
{"learn":[0.07815654983],"iteration":424,"passed_time":2.430369764,"remaining_time":3.288147327},
{"learn":[0.07802728479],"iteration":425,"passed_time":2.436263224,"remaining_time":3.282664532},
{"learn":[0.07777171477],"iteration":426,"passed_time":2.44061545,"remaining_time":3.2751116},
{"learn":[0.07753555754],"iteration":427,"passed_time":2.445720642,"remaining_time":3.268579924},
{"learn":[0.07738760614],"iteration":428,"passed_time":2.451425589,"remaining_time":3.262853174},
{"learn":[0.07715183102],"iteration":429,"passed_time":2.456401548,"remaining_time":3.256160192},
{"learn":[0.07695425312],"iteration":430,"passed_time":2.462064949,"remaining_time":3.250382728},
{"learn":[0.07672756595],"iteration":431,"passed_time":2.468065346,"remaining_time":3.245048881},
{"learn":[0.07660858983],"iteration":432,"passed_time":2.473416755,"remaining_time":3.238862125},
{"learn":[0.07639857829],"iteration":433,"passed_time":2.479528454,"remaining_time":3.233670748},
{"learn":[0.0762721885],"iteration":434,"passed_time":2.485346298,"remaining_time":3.228093467},
{"learn":[0.07616024921],"iteration":435,"passed_time":2.490939653,"remaining_time":3.222224689},
{"learn":[0.07585649152],"iteration":436,"passed_time":2.495390312,"remaining_time":3.214885002},
{"learn":[0.07570084073],"iteration":437,"passed_time":2.501050466,"remaining_time":3.209110416},
{"learn":[0.07560322093],"iteration":438,"passed_time":2.505090012,"remaining_time":3.201265368},
{"learn":[0.07541478684],"iteration":439,"passed_time":2.510592821,"remaining_time":3.195299954},
{"learn":[0.0753908523],"iteration":440,"passed_time":2.515636745,"remaining_time":3.188754967},
{"learn":[0.07535535783],"iteration":441,"passed_time":2.52058833,"remaining_time":3.182100199},
{"learn":[0.07533783547],"iteration":442,"passed_time":2.526956021,"remaining_time":3.177233643},
{"learn":[0.075261595],"iteration":443,"passed_time":2.53395268,"remaining_time":3.173147951},
{"learn":[0.07501148367],"iteration":444,"passed_time":2.540305001,"remaining_time":3.168245563},
{"learn":[0.07491647668],"iteration":445,"passed_time":2.547820601,"remaining_time":3.164781643},
{"learn":[0.07473116324],"iteration":446,"passed_time":2.554715932,"remaining_time":3.160532238},
{"learn":[0.0746885363],"iteration":447,"passed_time":2.559936565,"remaining_time":3.154207553},
{"learn":[0.07449965235],"iteration":448,"passed_time":2.567986598,"remaining_time":3.151359946},
{"learn":[0.07445299994],"iteration":449,"passed_time":2.574475039,"remaining_time":3.146580603},
{"learn":[0.07442944184],"iteration":450,"passed_time":2.579634322,"remaining_time":3.140175704},
{"learn":[0.07427864005],"iteration":451,"passed_time":2.584098586,"remaining_time":3.132933683},
{"learn":[0.07408582481],"iteration":452,"passed_time":2.589628582,"remaining_time":3.126990805},
{"learn":[0.0739440821],"iteration":453,"passed_time":2.595253404,"remaining_time":3.121163785},
{"learn":[0.07385026139],"iteration":454,"passed_time":2.600492489,"remaining_time":3.114875619},
{"learn":[0.07357540882],"iteration":455,"passed_time":2.606309853,"remaining_time":3.10928193},
{"learn":[0.07338704035],"iteration":456,"passed_time":2.612099232,"remaining_time":3.103654011},
{"learn":[0.07321893185],"iteration":457,"passed_time":2.617764275,"remaining_time":3.097878247},
{"learn":[0.07300324564],"iteration":458,"passed_time":2.623836013,"remaining_time":3.092582317},
{"learn":[0.07284373584],"iteration":459,"passed_time":2.628526203,"remaining_time":3.085661195},
{"learn":[0.0727612186],"iteration":460,"passed_time":2.633177234,"remaining_time":3.078703968},
{"learn":[0.07255735587],"iteration":461,"passed_time":2.638449861,"remaining_time":3.072480574},
{"learn":[0.07242661355],"iteration":462,"passed_time":2.643641929,"remaining_time":3.066167852},
{"learn":[0.07225496008],"iteration":463,"passed_time":2.649765308,"remaining_time":3.060935786},
{"learn":[0.07216460152],"iteration":464,"passed_time":2.655599648,"remaining_time":3.055367337},
{"learn":[0.07198881124],"iteration":465,"passed_time":2.66037088,"remaining_time":3.048579506},
{"learn":[0.07188744379],"iteration":466,"passed_time":2.665843125,"remaining_time":3.042600398},
{"learn":[0.07172376902],"iteration":467,"passed_time":2.671547369,"remaining_time":3.036887181},
{"learn":[0.07150939096],"iteration":468,"passed_time":2.677247395,"remaining_time":3.031169225},
{"learn":[0.07138129299],"iteration":469,"passed_time":2.683325721,"remaining_time":3.025877941},
{"learn":[0.07132522825],"iteration":470,"passed_time":2.690404354,"remaining_time":3.021706801},
{"learn":[0.07116385386],"iteration":471,"passed_time":2.697723753,"remaining_time":3.017792672},
{"learn":[0.07106246297],"iteration":472,"passed_time":2.703600881,"remaining_time":3.012257219},
{"learn":[0.07104495041],"iteration":473,"passed_time":2.708334413,"remaining_time":3.005451268},
{"learn":[0.07092048127],"iteration":474,"passed_time":2.713926146,"remaining_time":2.999602582},
{"learn":[0.07076849749],"iteration":475,"passed_time":2.719632553,"remaining_time":2.993881214},
{"learn":[0.07063101824],"iteration":476,"passed_time":2.725094383,"remaining_time":2.987891745},
{"learn":[0.07047578978],"iteration":477,"passed_time":2.730410599,"remaining_time":2.981745466},
{"learn":[0.07034302792],"iteration":478,"passed_time":2.736351615,"remaining_time":2.976282237},
{"learn":[0.07011179261],"iteration":479,"passed_time":2.742067194,"remaining_time":2.970572794},
{"learn":[0.06993729172],"iteration":480,"passed_time":2.747651021,"remaining_time":2.964721164},
{"learn":[0.06974003212],"iteration":481,"passed_time":2.752816489,"remaining_time":2.95842104},
{"learn":[0.06970705313],"iteration":482,"passed_time":2.758667282,"remaining_time":2.952859182},
{"learn":[0.06955275438],"iteration":483,"passed_time":2.764119146,"remaining_time":2.946870825},
{"learn":[0.06938967533],"iteration":484,"passed_time":2.769973485,"remaining_time":2.941312051},
{"learn":[0.06913408795],"iteration":485,"passed_time":2.774937302,"remaining_time":2.934810233},
{"learn":[0.06894360144],"iteration":486,"passed_time":2.781660892,"remaining_time":2.930168455},
{"learn":[0.06887735836],"iteration":487,"passed_time":2.788083217,"remaining_time":2.925202063},
{"learn":[0.06879672824],"iteration":488,"passed_time":2.793213635,"remaining_time":2.918879688},
{"learn":[0.06864381574],"iteration":489,"passed_time":2.798967235,"remaining_time":2.913210796},
{"learn":[0.06841239554],"iteration":490,"passed_time":2.805218806,"remaining_time":2.908057784},
{"learn":[0.06824751066],"iteration":491,"passed_time":2.811046764,"remaining_time":2.902462919},
{"learn":[0.06811176554],"iteration":492,"passed_time":2.815421156,"remaining_time":2.895372264},
{"learn":[0.06793618114],"iteration":493,"passed_time":2.820344276,"remaining_time":2.888854663},
{"learn":[0.06778878934],"iteration":494,"passed_time":2.824832606,"remaining_time":2.881899931},
{"learn":[0.06769806997],"iteration":495,"passed_time":2.83010919,"remaining_time":2.875756112},
{"learn":[0.06757110403],"iteration":496,"passed_time":2.83542965,"remaining_time":2.869660189},
{"learn":[0.06746000736],"iteration":497,"passed_time":2.840506289,"remaining_time":2.863321601},
{"learn":[0.06723263021],"iteration":498,"passed_time":2.846416182,"remaining_time":2.857824664},
{"learn":[0.06715733977],"iteration":499,"passed_time":2.851176346,"remaining_time":2.851176346},
{"learn":[0.06699313186],"iteration":500,"passed_time":2.85623658,"remaining_time":2.844834438},
{"learn":[0.0669064838],"iteration":501,"passed_time":2.862275971,"remaining_time":2.839468992},
{"learn":[0.0667855721],"iteration":502,"passed_time":2.867826917,"remaining_time":2.833618246},
{"learn":[0.06663717106],"iteration":503,"passed_time":2.872518986,"remaining_time":2.826923447},
{"learn":[0.06657388911],"iteration":504,"passed_time":2.878317573,"remaining_time":2.821321185},
{"learn":[0.06647824495],"iteration":505,"passed_time":2.883673444,"remaining_time":2.815285932},
{"learn":[0.06634832829],"iteration":506,"passed_time":2.887822447,"remaining_time":2.808079815},
{"learn":[0.06621542861],"iteration":507,"passed_time":2.892997461,"remaining_time":2.80187943},
{"learn":[0.06619486127],"iteration":508,"passed_time":2.897742456,"remaining_time":2.795268263},
{"learn":[0.0661342823],"iteration":509,"passed_time":2.903314322,"remaining_time":2.789458858},
{"learn":[0.06605501142],"iteration":510,"passed_time":2.908142949,"remaining_time":2.782939143},
{"learn":[0.06591156133],"iteration":511,"passed_time":2.91321233,"remaining_time":2.776655502},
{"learn":[0.06587123647],"iteration":512,"passed_time":2.919873208,"remaining_time":2.771887431},
{"learn":[0.06581322915],"iteration":513,"passed_time":2.926272265,"remaining_time":2.766864437},
{"learn":[0.06574997391],"iteration":514,"passed_time":2.930774622,"remaining_time":2.760049886},
{"learn":[0.06562034188],"iteration":515,"passed_time":2.93630008,"remaining_time":2.754203951},
{"learn":[0.06551350591],"iteration":516,"passed_time":2.942651364,"remaining_time":2.749130772},
{"learn":[0.06541116934],"iteration":517,"passed_time":2.947944234,"remaining_time":2.743067801},
{"learn":[0.06522773681],"iteration":518,"passed_time":2.954264789,"remaining_time":2.737960238},
{"learn":[0.06504736153],"iteration":519,"passed_time":2.960714368,"remaining_time":2.732967109},
{"learn":[0.0649079869],"iteration":520,"passed_time":2.966458999,"remaining_time":2.72732027},
{"learn":[0.06465274525],"iteration":521,"passed_time":2.971794951,"remaining_time":2.721298825},
{"learn":[0.06446937898],"iteration":522,"passed_time":2.977411528,"remaining_time":2.715535944},
{"learn":[0.06433940845],"iteration":523,"passed_time":2.983744542,"remaining_time":2.710424431},
{"learn":[0.06413890613],"iteration":524,"passed_time":2.989500194,"remaining_time":2.70478589},
{"learn":[0.06399712788],"iteration":525,"passed_time":2.994851039,"remaining_time":2.698782115},
{"learn":[0.06390182603],"iteration":526,"passed_time":3.000192832,"remaining_time":2.692772693},
{"learn":[0.06389431776],"iteration":527,"passed_time":3.005529394,"remaining_time":2.686761125},
{"learn":[0.06378852658],"iteration":528,"passed_time":3.010483313,"remaining_time":2.680411419},
{"learn":[0.06368459059],"iteration":529,"passed_time":3.016078773,"remaining_time":2.674635893},
{"learn":[0.06350055848],"iteration":530,"passed_time":3.02130734,"remaining_time":2.668536992},
{"learn":[0.0634837022],"iteration":531,"passed_time":3.027051131,"remaining_time":2.662894604},
{"learn":[0.06334691633],"iteration":532,"passed_time":3.032559275,"remaining_time":2.657045368},
{"learn":[0.06323336839],"iteration":533,"passed_time":3.036941514,"remaining_time":2.650214879},
{"learn":[0.06307927749],"iteration":534,"passed_time":3.043071387,"remaining_time":2.644912514},
{"learn":[0.06298748021],"iteration":535,"passed_time":3.0484589,"remaining_time":2.638964421},
{"learn":[0.06283805179],"iteration":536,"passed_time":3.053478694,"remaining_time":2.63270137},
{"learn":[0.06269915966],"iteration":537,"passed_time":3.059101231,"remaining_time":2.626960537},
{"learn":[0.06252689871],"iteration":538,"passed_time":3.064857957,"remaining_time":2.621334913},
{"learn":[0.06240950855],"iteration":539,"passed_time":3.070244655,"remaining_time":2.615393595},
{"learn":[0.06223133955],"iteration":540,"passed_time":3.074585789,"remaining_time":2.60856724},
{"learn":[0.06209357937],"iteration":541,"passed_time":3.080084168,"remaining_time":2.60272795},
{"learn":[0.06204700516],"iteration":542,"passed_time":3.085713848,"remaining_time":2.597000421},
{"learn":[0.06190506005],"iteration":543,"passed_time":3.091265915,"remaining_time":2.591208194},
{"learn":[0.06189893421],"iteration":544,"passed_time":3.096527153,"remaining_time":2.585174045},
{"learn":[0.06177921908],"iteration":545,"passed_time":3.101227215,"remaining_time":2.578676109},
{"learn":[0.06164138011],"iteration":546,"passed_time":3.106427008,"remaining_time":2.572598601},
{"learn":[0.06138713696],"iteration":547,"passed_time":3.11172972,"remaining_time":2.566609185},
{"learn":[0.06136531188],"iteration":548,"passed_time":3.117202636,"remaining_time":2.560762093},
{"learn":[0.0613326488],"iteration":549,"passed_time":3.12298279,"remaining_time":2.555167738},
{"learn":[0.06117160468],"iteration":550,"passed_time":3.128655045,"remaining_time":2.549484782},
{"learn":[0.06114103259],"iteration":551,"passed_time":3.132669956,"remaining_time":2.542456776},
{"learn":[0.06100610783],"iteration":552,"passed_time":3.138423492,"remaining_time":2.536845029},
{"learn":[0.06088175859],"iteration":553,"passed_time":3.143114889,"remaining_time":2.530377691},
{"learn":[0.06084667292],"iteration":554,"passed_time":3.14809015,"remaining_time":2.524144354},
{"learn":[0.06070168408],"iteration":555,"passed_time":3.15361526,"remaining_time":2.518354632},
{"learn":[0.06057037009],"iteration":556,"passed_time":3.15844974,"remaining_time":2.51201658},
{"learn":[0.06045153791],"iteration":557,"passed_time":3.163696063,"remaining_time":2.506010143},
{"learn":[0.06040071673],"iteration":558,"passed_time":3.168919967,"remaining_time":2.49998874},
{"learn":[0.06028705193],"iteration":559,"passed_time":3.174233822,"remaining_time":2.49404086},
{"learn":[0.06025915019],"iteration":560,"passed_time":3.180058859,"remaining_time":2.488495257},
{"learn":[0.06018034206],"iteration":561,"passed_time":3.185140798,"remaining_time":2.482369519},
{"learn":[0.06001662167],"iteration":562,"passed_time":3.191101512,"remaining_time":2.476929593},
{"learn":[0.05988306493],"iteration":563,"passed_time":3.196150789,"remaining_time":2.470783234},
{"learn":[0.05979325702],"iteration":564,"passed_time":3.201084376,"remaining_time":2.464551687},
{"learn":[0.05970230109],"iteration":565,"passed_time":3.206077902,"remaining_time":2.458370688},
{"learn":[0.05948966738],"iteration":566,"passed_time":3.211446919,"remaining_time":2.452480628},
{"learn":[0.05946722727],"iteration":567,"passed_time":3.215934415,"remaining_time":2.44592195},
{"learn":[0.05930517461],"iteration":568,"passed_time":3.221160334,"remaining_time":2.439929884},
{"learn":[0.05929568978],"iteration":569,"passed_time":3.227100136,"remaining_time":2.43447905},
{"learn":[0.05919978459],"iteration":570,"passed_time":3.231522779,"remaining_time":2.427886641},
{"learn":[0.05906544661],"iteration":571,"passed_time":3.237504506,"remaining_time":2.422468407},
{"learn":[0.05901437065],"iteration":572,"passed_time":3.243279231,"remaining_time":2.416893947},
{"learn":[0.05886089195],"iteration":573,"passed_time":3.24811492,"remaining_time":2.410621874},
{"learn":[0.058774673],"iteration":574,"passed_time":3.25328617,"remaining_time":2.404602822},
{"learn":[0.05867543364],"iteration":575,"passed_time":3.258997979,"remaining_time":2.398984623},
{"learn":[0.05856222971],"iteration":576,"passed_time":3.264774752,"remaining_time":2.393413726},
{"learn":[0.05844714211],"iteration":577,"passed_time":3.270486149,"remaining_time":2.387794386},
{"learn":[0.05833957583],"iteration":578,"passed_time":3.276418128,"remaining_time":2.382335116},
{"learn":[0.05833414483],"iteration":579,"passed_time":3.280838049,"remaining_time":2.375779277},
{"learn":[0.0582616967],"iteration":580,"passed_time":3.286891452,"remaining_time":2.370408809},
{"learn":[0.05821325451],"iteration":581,"passed_time":3.291553422,"remaining_time":2.36403665},
{"learn":[0.0580862605],"iteration":582,"passed_time":3.296121694,"remaining_time":2.357603339},
{"learn":[0.05799714195],"iteration":583,"passed_time":3.302186692,"remaining_time":2.352242575},
{"learn":[0.05792275884],"iteration":584,"passed_time":3.307784803,"remaining_time":2.346548194},
{"learn":[0.057817845],"iteration":585,"passed_time":3.313589197,"remaining_time":2.340999877},
{"learn":[0.05766591775],"iteration":586,"passed_time":3.31813389,"remaining_time":2.33456439},
{"learn":[0.05755451072],"iteration":587,"passed_time":3.323683262,"remaining_time":2.328839292},
{"learn":[0.05748953981],"iteration":588,"passed_time":3.328804468,"remaining_time":2.322816021},
{"learn":[0.05736574164],"iteration":589,"passed_time":3.333819123,"remaining_time":2.316721763},
{"learn":[0.0572611968],"iteration":590,"passed_time":3.338713927,"remaining_time":2.310548217},
{"learn":[0.05720731113],"iteration":591,"passed_time":3.34450999,"remaining_time":2.305000128},
{"learn":[0.05712542807],"iteration":592,"passed_time":3.348891805,"remaining_time":2.298480547},
{"learn":[0.05709038291],"iteration":593,"passed_time":3.353839951,"remaining_time":2.292355253},
{"learn":[0.05702295993],"iteration":594,"passed_time":3.359161142,"remaining_time":2.286487836},
{"learn":[0.05685395195],"iteration":595,"passed_time":3.365438774,"remaining_time":2.281270578},
{"learn":[0.05679364273],"iteration":596,"passed_time":3.370241666,"remaining_time":2.275054257},
{"learn":[0.05668059958],"iteration":597,"passed_time":3.37561907,"remaining_time":2.269228873},
{"learn":[0.05665278158],"iteration":598,"passed_time":3.381100877,"remaining_time":2.263474877},
{"learn":[0.05654352451],"iteration":599,"passed_time":3.385938499,"remaining_time":2.257292333},
{"learn":[0.05634922888],"iteration":600,"passed_time":3.391062938,"remaining_time":2.25130468},
{"learn":[0.05616942866],"iteration":601,"passed_time":3.396067914,"remaining_time":2.245240914},
{"learn":[0.05609361168],"iteration":602,"passed_time":3.401295972,"remaining_time":2.23932753},
{"learn":[0.05599864608],"iteration":603,"passed_time":3.406814093,"remaining_time":2.233606591},
{"learn":[0.05585430432],"iteration":604,"passed_time":3.412510236,"remaining_time":2.228002551},
{"learn":[0.05574832566],"iteration":605,"passed_time":3.41770935,"remaining_time":2.222075056},
{"learn":[0.05567218023],"iteration":606,"passed_time":3.42207443,"remaining_time":2.215609969},
{"learn":[0.05559513227],"iteration":607,"passed_time":3.426262419,"remaining_time":2.209037612},
{"learn":[0.05548216889],"iteration":608,"passed_time":3.43217169,"remaining_time":2.203578211},
{"learn":[0.05542995067],"iteration":609,"passed_time":3.437263312,"remaining_time":2.197594577},
{"learn":[0.0554086726],"iteration":610,"passed_time":3.443849721,"remaining_time":2.192565534},
{"learn":[0.05532267679],"iteration":611,"passed_time":3.449641898,"remaining_time":2.18702787},
{"learn":[0.05524242021],"iteration":612,"passed_time":3.455656989,"remaining_time":2.181630106},
{"learn":[0.05516780856],"iteration":613,"passed_time":3.460399255,"remaining_time":2.17543015},
{"learn":[0.05509584531],"iteration":614,"passed_time":3.465046156,"remaining_time":2.169175236},
{"learn":[0.05493973961],"iteration":615,"passed_time":3.470562302,"remaining_time":2.163467409},
{"learn":[0.05484710541],"iteration":616,"passed_time":3.475062926,"remaining_time":2.157129823},
{"learn":[0.05474226314],"iteration":617,"passed_time":3.480036678,"remaining_time":2.151090633},
{"learn":[0.05463991228],"iteration":618,"passed_time":3.485191432,"remaining_time":2.145166293},
{"learn":[0.05458309832],"iteration":619,"passed_time":3.491572908,"remaining_time":2.139996298},
{"learn":[0.05448339169],"iteration":620,"passed_time":3.496587265,"remaining_time":2.133988041},
{"learn":[0.0544519345],"iteration":621,"passed_time":3.502226466,"remaining_time":2.128362708},
{"learn":[0.05436067132],"iteration":622,"passed_time":3.508045335,"remaining_time":2.122846053},
{"learn":[0.05430757522],"iteration":623,"passed_time":3.513280408,"remaining_time":2.116976656},
{"learn":[0.05419109915],"iteration":624,"passed_time":3.518812844,"remaining_time":2.111287707},
{"learn":[0.0541809347],"iteration":625,"passed_time":3.523671554,"remaining_time":2.105196743},
{"learn":[0.05402336243],"iteration":626,"passed_time":3.529573245,"remaining_time":2.099730176},
{"learn":[0.05395706173],"iteration":627,"passed_time":3.535337413,"remaining_time":2.09418076},
{"learn":[0.05386788924],"iteration":628,"passed_time":3.539862574,"remaining_time":2.087899865},
{"learn":[0.0537170192],"iteration":629,"passed_time":3.546559518,"remaining_time":2.082900035},
{"learn":[0.05365547317],"iteration":630,"passed_time":3.551461223,"remaining_time":2.07684,
{"l,
{"learn":[0.05349935531],"iteration":631,"passed_time":3.558383451,"remaining_time":2.071970111},
{"learn":[0.05338713296],"iteration":632,"passed_time":3.564650387,"remaining_time":2.066708834},
{"learn":[0.05327886479],"iteration":633,"passed_time":3.570329856,"remaining_time":2.061105248},
{"learn":[0.05317066822],"iteration":634,"passed_time":3.575522122,"remaining_time":2.05522,
{"l,
{"learn":[0.05311776256],"iteration":635,"passed_time":3.582188778,"remaining_time":2.05018,
{"l,
{"learn":[0.05296878463],"iteration":636,"passed_time":3.586651402,"remaining_time":2.04388,
{"l,
{"learn":[0.05289393937],"iteration":637,"passed_time":3.591513728,"remaining_time":2.03781,
{"l,
{"learn":[0.05287518148],"iteration":638,"passed_time":3.59703207,"remaining_time":2.032126,
{",
{"learn":[0.0528144996],"iteration":639,"passed_time":3.602800697,"remaining_time":2.0265753,
{,
{"learn":[0.05273292364],"iteration":640,"passed_time":3.60758821,"remaining_time":2.0204745,
,
{"learn":[0.05269504839],"iteration":641,"passed_time":3.61316147,"remaining_time":2.014815898,,
{"learn":[0.05260008071],"iteration":642,"passed_time":3.618603359,"remaining_time":2.009084602,,
{"learn":[0.05259478662],"iteration":643,"passed_time":3.624468332,"remaining_time":2.003588084,,
{"learn":[0.05248141395],"iteration":644,"passed_time":3.629251482,"remaining_time":1.997495002,,
{"learn":[0.05233244073],"iteration":645,"passed_time":3.635421652,"remaining_time":1.99216604,
,
{"learn":[0.05220906348],"iteration":646,"passed_time":3.640248263,"remaining_time":1.98610144,
,
{"learn":[0.05209734488],"iteration":647,"passed_time":3.646263599,"remaining_time":1.98068639,
,
{"learn":[0.05205976915],"iteration":648,"passed_time":3.652118853,"remaining_time":1.97518292,
,
{"learn":[0.05202178623],"iteration":649,"passed_time":3.657367805,"remaining_time":1.96935189,
,
{"learn":[0.05194087],"iteration":650,"passed_time":3.663085559,"remaining_time":1.963773979},
{"learn":[0.05193120183],"iteration":651,"passed_time":3.666961621,"remaining_time":1.957212644},
{"learn":[0.05174998084],"iteration":652,"passed_time":3.672889278,"remaining_time":1.951749739},
{"learn":[0.05168826379],"iteration":653,"passed_time":3.678024746,"remaining_time":1.945866303},
{"learn":[0.05154977813],"iteration":654,"passed_time":3.684185669,"remaining_time":1.940525276,,
{"learn":[0.05147491267],"iteration":655,"passed_time":3.68972779,"remaining_time":1.934857256},
{"learn":[0.05144522588],"iteration":656,"passed_time":3.695655711,"remaining_time":1.929391033},
{"learn":[0.05142146648],"iteration":657,"passed_time":3.70203861,"remaining_time":1.924159886},
{"learn":[0.05130141638],"iteration":658,"passed_time":3.706779076,"remaining_time":1.918075364,,
{"learn":[0.05121711987],"iteration":659,"passed_time":3.7125964,"remaining_time":1.912549661,,
{"learn":[0.05118034932],"iteration":660,"passed_time":3.716988923,"remaining_time":1.906292353,,
{"learn":[0.05106222469],"iteration":661,"passed_time":3.722086931,"remaining_time":1.90040088},
{"learn":[0.05096840508],"iteration":662,"passed_time":3.728228385,"remaining_time":1.89504218,
,
{"learn":[0.05087287085],"iteration":663,"passed_time":3.732998515,"remaining_time":1.8889872},
{"learn":[0.05073804337],"iteration":664,"passed_time":3.737539497,"remaining_time":1.882820649},
{"learn":[0.05062191297],"iteration":665,"passed_time":3.74310284,"remaining_time":1.877171695},
{"learn":[0.05053113359],"iteration":666,"passed_time":3.747884474,"remaining_time":1.871132728},
{"learn":[0.04676973985],"iteration":667,"passed_time":3.755980501,"remaining_time":1.8667448},
{"learn":[0.04671781694],"iteration":668,"passed_time":3.761773992,"remaining_time":1.861206564},
{"learn":[0.0466745297],"iteration":669,"passed_time":3.766062823,"remaining_time":1.854926465},
{"learn":[0.04663895297],"iteration":670,"passed_time":3.771353697,"remaining_time":1.849143616},,
{"learn":[0.05015613041],"iteration":671,"passed_time":3.774322604,"remaining_time":1.84222889},
{"learn":[0.0501273248],"iteration":672,"passed_time":3.780125126,"remaining_time":1.836702699},,
{"learn":[0.04640516191],"iteration":673,"passed_time":3.787531251,"remaining_time":1.8319513,
{,
{"learn":[0.04636833451],"iteration":674,"passed_time":3.793919511,"remaining_time":1.8267019,
{,
{"learn":[0.04633903751],"iteration":675,"passed_time":3.799144907,"remaining_time":1.8208919,
{,
{"learn":[0.04622854881],"iteration":676,"passed_time":3.80413235,"remaining_time":1.81497008,
,
{"learn":[0.0461467619],"iteration":677,"passed_time":3.810047709,"remaining_time":1.80949168,
,
{"learn":[0.04601253938],"iteration":678,"passed_time":3.815125989,"remaining_time":1.80361626,
,
{"learn":[0.04591059815],"iteration":679,"passed_time":3.819753737,"remaining_time":1.79753117,,
{"learn":[0.04586586001],"iteration":680,"passed_time":3.82517959,"remaining_time":1.791824213},
{"learn":[0.04585411386],"iteration":681,"passed_time":3.829432561,"remaining_time":1.785571194},
{"learn":[0.04574493597],"iteration":682,"passed_time":3.835557706,"remaining_time":1.780192962},
{"learn":[0.04564541735],"iteration":683,"passed_time":3.841294438,"remaining_time":1.774633103},
{"learn":[0.04556899601],"iteration":684,"passed_time":3.846397957,"remaining_time":1.768781542},
{"learn":[0.04552996993],"iteration":685,"passed_time":3.851429655,"remaining_time":1.762899288,,
{"learn":[0.04548552556],"iteration":686,"passed_time":3.856372243,"remaining_time":1.75697891,
,
{"learn":[0.04537156511],"iteration":687,"passed_time":3.862093207,"remaining_time":1.75141436,
,
{"learn":[0.04532622806],"iteration":688,"passed_time":3.868676472,"remaining_time":1.74623858,
,
{"learn":[0.04527314282],"iteration":689,"passed_time":3.873584931,"remaining_time":1.74030627,
,
{"learn":[0.04519792189],"iteration":690,"passed_time":3.877919815,"remaining_time":1.73412043,
,
{"learn":[0.0450613977],"iteration":691,"passed_time":3.883282046,"remaining_time":1.728397211,,
{"learn":[0.04505353405],"iteration":692,"passed_time":3.888413712,"remaining_time":1.722572885,,
{"learn":[0.0449520064],"iteration":693,"passed_time":3.894475873,"remaining_time":1.717160832},
{"learn":[0.04490690014],"iteration":694,"passed_time":3.899284276,"remaining_time":1.711196697},
{"learn":[0.04485957241],"iteration":695,"passed_time":3.904262169,"remaining_time":1.705309913},
{"learn":[0.04478752905],"iteration":696,"passed_time":3.909871826,"remaining_time":1.69970037,
,
{"learn":[0.04470123589],"iteration":697,"passed_time":3.914986099,"remaining_time":1.69387650,
,
{"learn":[0.04460365634],"iteration":698,"passed_time":3.920519842,"remaining_time":1.68823529,
,
{"learn":[0.04454387289],"iteration":699,"passed_time":3.92639488,"remaining_time":1.682740663,,
{"learn":[0.04446980533],"iteration":700,"passed_time":3.93214577,"remaining_time":1.67719199},
{"learn":[0.04433792058],"iteration":701,"passed_time":3.937307245,"remaining_time":1.671392534},
{"learn":[0.04425767478],"iteration":702,"passed_time":3.942577124,"remaining_time":1.665640691},
{"learn":[0.04419409011],"iteration":703,"passed_time":3.947986674,"remaining_time":1.659948943},
{"learn":[0.04412609685],"iteration":704,"passed_time":3.953357365,"remaining_time":1.654241734},
{"learn":[0.04411369415],"iteration":705,"passed_time":3.959834141,"remaining_time":1.648996087},
{"learn":[0.04401886425],"iteration":706,"passed_time":3.965083892,"remaining_time":1.643238445},
{"learn":[0.0439184018],"iteration":707,"passed_time":3.969739208,"remaining_time":1.637237074},
{"learn":[0.04384884151],"iteration":708,"passed_time":3.975626732,"remaining_time":1.631745246},
{"learn":[0.04378370923],"iteration":709,"passed_time":3.980707296,"remaining_time":1.625922698},
{"learn":[0.04371362352],"iteration":710,"passed_time":3.985934364,"remaining_time":1.620161788},
{"learn":[0.04360458682],"iteration":711,"passed_time":3.991731885,"remaining_time":1.614633122},
{"learn":[0.04352994242],"iteration":712,"passed_time":3.997046603,"remaining_time":1.608909362},
{"learn":[0.04349824947],"iteration":713,"passed_time":4.002936713,"remaining_time":1.603417227},
{"learn":[0.04340275982],"iteration":714,"passed_time":4.009023953,"remaining_time":1.598002555},
{"learn":[0.04333716131],"iteration":715,"passed_time":4.014228518,"remaining_time":1.592235893},
{"learn":[0.04323788401],"iteration":716,"passed_time":4.019856969,"remaining_time":1.586638106},
{"learn":[0.0431540875],"iteration":717,"passed_time":4.025653522,"remaining_time":1.581106258},
{"learn":[0.04305190877],"iteration":718,"passed_time":4.030480396,"remaining_time":1.575194703},
{"learn":[0.04297520721],"iteration":719,"passed_time":4.036253539,"remaining_time":1.569654154,,
{"learn":[0.04293069918],"iteration":720,"passed_time":4.04212448,"remaining_time":1.564150804},
{"learn":[0.04290216179],"iteration":721,"passed_time":4.046856106,"remaining_time":1.558207753},
{"learn":[0.04288047149],"iteration":722,"passed_time":4.051968476,"remaining_time":1.552413925},
{"learn":[0.04279603337],"iteration":723,"passed_time":4.057620323,"remaining_time":1.546827637},
{"learn":[0.04643465789],"iteration":724,"passed_time":4.061722617,"remaining_time":1.540653406},
{"learn":[0.0463644065],"iteration":725,"passed_time":4.066918647,"remaining_time":1.534897671,,
{"learn":[0.04630076346],"iteration":726,"passed_time":4.07202787,"remaining_time":1.529110878,,
{"learn":[0.04625350161],"iteration":727,"passed_time":4.077190349,"remaining_time":1.523345845,,
{"learn":[0.0461717405],"iteration":728,"passed_time":4.083585652,"remaining_time":1.518040757},
{"learn":[0.04608568869],"iteration":729,"passed_time":4.089111866,"remaining_time":1.512411238},
{"learn":[0.04596739329],"iteration":730,"passed_time":4.094327146,"remaining_time":1.506667582},
{"learn":[0.04593383242],"iteration":731,"passed_time":4.100404646,"remaining_time":1.501241045},
{"learn":[0.04586246628],"iteration":732,"passed_time":4.104552184,"remaining_time":1.495109732},
{"learn":[0.04576246674],"iteration":733,"passed_time":4.110138316,"remaining_time":1.489505166},
{"learn":[0.04575494893],"iteration":734,"passed_time":4.115265758,"remaining_time":1.4837352,
{,
{"learn":[0.04567847374],"iteration":735,"passed_time":4.121289019,"remaining_time":1.4782884,
{,
{"learn":[0.04559503904],"iteration":736,"passed_time":4.126660658,"remaining_time":1.4726075,
{,
{"learn":[0.04546383775],"iteration":737,"passed_time":4.131444346,"remaining_time":1.4667187,
{,
{"learn":[0.0453943278],"iteration":738,"passed_time":4.137329368,"remaining_time":1.46122187,
,
{"learn":[0.04532372043],"iteration":739,"passed_time":4.142501313,"remaining_time":1.45547343,
,
{"learn":[0.04525100033],"iteration":740,"passed_time":4.147291804,"remaining_time":1.44959322,
,
{"learn":[0.04524548019],"iteration":741,"passed_time":4.153668762,"remaining_time":1.4442675,
{,
{"learn":[0.04520805887],"iteration":742,"passed_time":4.158482557,"remaining_time":1.43839,
{"l,
{"learn":[0.04515670835],"iteration":743,"passed_time":4.163110016,"remaining_time":1.43246,
{"l,
{"learn":[0.04512549941],"iteration":744,"passed_time":4.168199928,"remaining_time":1.42669,
{"l,
{"learn":[0.04502041862],"iteration":745,"passed_time":4.172987843,"remaining_time":1.4208,
{"le,
{"learn":[0.04501639885],"iteration":746,"passed_time":4.179140631,"remaining_time":1.415,
{"le,
{"learn":[0.04495823706],"iteration":747,"passed_time":4.185108325,"remaining_time":1.4099,
{"le,
{"learn":[0.04492570208],"iteration":748,"passed_time":4.189436829,"remaining_time":1.4039,
{"le,
{"learn":[0.04485235088],"iteration":749,"passed_time":4.195401729,"remaining_time":1.3984,
{"le,
{"learn":[0.04478957969],"iteration":750,"passed_time":4.200743696,"remaining_time":1.3927,
{"le,
{"learn":[0.04469739921],"iteration":751,"passed_time":4.205851396,"remaining_time":1.3870,
{"le,
{"learn":[0.04464221222],"iteration":752,"passed_time":4.211865807,"remaining_time":1.3815,
{"l,
{"learn":[0.04462380558],"iteration":753,"passed_time":4.217123117,"remaining_time":1.37587,
{"l,
{"learn":[0.04460365773],"iteration":754,"passed_time":4.222597387,"remaining_time":1.37024,
{"l,
{"learn":[0.0445448357],"iteration":755,"passed_time":4.229115704,"remaining_time":1.364952,
{",
{"learn":[0.04449092832],"iteration":756,"passed_time":4.236534044,"remaining_time":1.359944218},
{"learn":[0.04441427356],"iteration":757,"passed_time":4.241893256,"remaining_time":1.354271,
{",
{"learn":[0.04433942925],"iteration":758,"passed_time":4.247560004,"remaining_time":1.348698,
{",
{"learn":[0.04430944392],"iteration":759,"passed_time":4.252706861,"remaining_time":1.342960,
{",
{"learn":[0.04429080299],"iteration":760,"passed_time":4.258855411,"remaining_time":1.337538,
{",
{"learn":[0.04420248497],"iteration":761,"passed_time":4.265483213,"remaining_time":1.332263,
{",
{"learn":[0.044166768],"iteration":762,"passed_time":4.272214916,"remaining_time":1.32701826,
,
{"learn":[0.04409130925],"iteration":763,"passed_time":4.280246576,"remaining_time":1.3221704,
{,
{"learn":[0.04396995606],"iteration":764,"passed_time":4.286788777,"remaining_time":1.316856683},
{"learn":[0.04390233501],"iteration":765,"passed_time":4.292388588,"remaining_time":1.31125,
{"l,
{"learn":[0.04382213319],"iteration":766,"passed_time":4.297638475,"remaining_time":1.30554,
{"l,
{"learn":[0.04379607208],"iteration":767,"passed_time":4.303491253,"remaining_time":1.300012983},
{"learn":[0.04370904706],"iteration":768,"passed_time":4.309687992,"remaining_time":1.29458768},
{"learn":[0.04362815362],"iteration":769,"passed_time":4.317476593,"remaining_time":1.289635866},
{"learn":[0.04356800459],"iteration":770,"passed_time":4.324326451,"remaining_time":1.284397869},
{"learn":[0.04353287983],"iteration":771,"passed_time":4.330612973,"remaining_time":1.278989324},
{"learn":[0.04344792655],"iteration":772,"passed_time":4.336213977,"remaining_time":1.273377196},
{"learn":[0.04338954905],"iteration":773,"passed_time":4.341304803,"remaining_time":1.267616131},
{"learn":[0.04334791521],"iteration":774,"passed_time":4.34665091,"remaining_time":1.261930909},
{"learn":[0.04326431736],"iteration":775,"passed_time":4.351904713,"remaining_time":1.256219917},
{"learn":[0.04317778077],"iteration":776,"passed_time":4.357998832,"remaining_time":1.250751273},
{"learn":[0.04308936022],"iteration":777,"passed_time":4.363108948,"remaining_time":1.24500024},
{"learn":[0.04308399723],"iteration":778,"passed_time":4.369188525,"remaining_time":1.239525885},
{"learn":[0.04305730126],"iteration":779,"passed_time":4.374912661,"remaining_time":1.233949725},
{"learn":[0.04297698481],"iteration":780,"passed_time":4.379816113,"remaining_time":1.2281430,
{,
{"learn":[0.04296222979],"iteration":781,"passed_time":4.385159256,"remaining_time":1.222461,
{",
{"learn":[0.04292400655],"iteration":782,"passed_time":4.389954259,"remaining_time":1.216628,
{",
{"learn":[0.04287571537],"iteration":783,"passed_time":4.39496166,"remaining_time":1.2108567,
{,
{"learn":[0.04280525781],"iteration":784,"passed_time":4.400024166,"remaining_time":1.2051021,
,
{"learn":[0.04272902201],"iteration":785,"passed_time":4.405639127,"remaining_time":1.1994997,
{,
{"learn":[0.04272050182],"iteration":786,"passed_time":4.410596575,"remaining_time":1.1937,
{"le,
{"learn":[0.0426962582],"iteration":787,"passed_time":4.416151537,"remaining_time":1.18810,
{"l,
{"learn":[0.04257746197],"iteration":788,"passed_time":4.422321206,"remaining_time":1.18264,
{"l,
{"learn":[0.04249132893],"iteration":789,"passed_time":4.428177712,"remaining_time":1.1771,
{"le,
{"learn":[0.04244424825],"iteration":790,"passed_time":4.433465825,"remaining_time":1.1714,
{"le,
{"learn":[0.04235057021],"iteration":791,"passed_time":4.439484491,"remaining_time":1.165,
{"le,
{"learn":[0.0423235665],"iteration":792,"passed_time":4.445152028,"remaining_time":1.160,
{"lea,
{"learn":[0.04224815809],"iteration":793,"passed_time":4.45059177,"remaining_time":1.154,
{"lea,
{"learn":[0.04213382192],"iteration":794,"passed_time":4.455815346,"remaining_time":1.148,
{"lea,
{"learn":[0.04211495113],"iteration":795,"passed_time":4.461341608,"remaining_time":1.143,
{"lea,
{"learn":[0.04205193771],"iteration":796,"passed_time":4.467011711,"remaining_time":1.137,
{"lea,
{"learn":[0.04201095483],"iteration":797,"passed_time":4.472210855,"remaining_time":1.132,
{"lea,
{"learn":[0.04192270003],"iteration":798,"passed_time":4.478657852,"remaining_time":1.12,
{"lear,
{"learn":[0.04187959782],"iteration":799,"passed_time":4.482809832,"remaining_time":1.1,
{"learn,
{"learn":[0.04182559862],"iteration":800,"passed_time":4.488375454,"remaining_time":1.1,
{"learn,
{"learn":[0.04179033289],"iteration":801,"passed_time":4.493445565,"remaining_time":1.1,
{"learn,
{"learn":[0.04172908086],"iteration":802,"passed_time":4.498945486,"remaining_time":1.1,
{"learn,
{"learn":[0.04167321763],"iteration":803,"passed_time":4.506060439,"remaining_time":1.098492346},
{"learn":[0.04157447487],"iteration":804,"passed_time":4.512033276,"remaining_time":1.092977005},
{"learn":[0.04147013855],"iteration":805,"passed_time":4.517721246,"remaining_time":1.087391962},
{"learn":[0.04142159287],"iteration":806,"passed_time":4.523087961,"remaining_time":1.081729835},
{"learn":[0.04136934169],"iteration":807,"passed_time":4.5289679,"remaining_time":1.076190392},
{"learn":[0.04131442889],"iteration":808,"passed_time":4.53409546,"remaining_time":1.070472476},
{"learn":[0.04123883262],"iteration":809,"passed_time":4.539173653,"remaining_time":1.064744437},
{"learn":[0.04120067427],"iteration":810,"passed_time":4.545912328,"remaining_time":1.059404969},
{"learn":[0.04112713605],"iteration":811,"passed_time":4.550521343,"remaining_time":1.053568981},
{"learn":[0.04108930537],"iteration":812,"passed_time":4.555732163,"remaining_time":1.047874433},
{"learn":[0.04097121589],"iteration":813,"passed_time":4.560421977,"remaining_time":1.042062024},
{"learn":[0.04091374457],"iteration":814,"passed_time":4.564909068,"remaining_time":1.036206353},
{"learn":[0.04090890963],"iteration":815,"passed_time":4.570154136,"remaining_time":1.030524952},
{"learn":[0.04080839558],"iteration":816,"passed_time":4.575534496,"remaining_time":1.024874924},
{"learn":[0.04072088103],"iteration":817,"passed_time":4.580745815,"remaining_time":1.019187944},
{"learn":[0.04064030087],"iteration":818,"passed_time":4.585760965,"remaining_time":1.013458773},
{"learn":[0.0405385622],"iteration":819,"passed_time":4.591549344,"remaining_time":1.007901076},
{"learn":[0.04044780939],"iteration":820,"passed_time":4.596977646,"remaining_time":1.00226431},
{"learn":[0.04040691084],"iteration":821,"passed_time":4.602244447,"remaining_time":0.9965930797},
{"learn":[0.0403329261],"iteration":822,"passed_time":4.607089061,"remaining_time":0.9908320337},
{"learn":[0.04028100339],"iteration":823,"passed_time":4.612312334,"remaining_time":0.9851540907},
{"learn":[0.0402057024],"iteration":824,"passed_time":4.618254553,"remaining_time":0.9796297538},
{"learn":[0.04017745342],"iteration":825,"passed_time":4.623608557,"remaining_time":0.9739804951},
{"learn":[0.04010494169],"iteration":826,"passed_time":4.628427065,"remaining_time":0.9682199302},
{"learn":[0.04000473225],"iteration":827,"passed_time":4.633663762,"remaining_time":0.962548511},
{"learn":[0.03990624826],"iteration":828,"passed_time":4.639552895,"remaining_time":0.9570127202},
{"learn":[0.0398027898],"iteration":829,"passed_time":4.644329097,"remaining_time":0.9512481283},
{"learn":[0.0397060994],"iteration":830,"passed_time":4.649848574,"remaining_time":0.9456370746},
{"learn":[0.03969841767],"iteration":831,"passed_time":4.654533745,"remaining_time":0.9398577754},
{"learn":[0.03958358002],"iteration":832,"passed_time":4.660142509,"remaining_time":0.9342662653},
{"learn":[0.03954683455],"iteration":833,"passed_time":4.664979589,"remaining_time":0.9285211173},
{"learn":[0.03949040424],"iteration":834,"passed_time":4.670640281,"remaining_time":0.9229408938},
{"learn":[0.03943996113],"iteration":835,"passed_time":4.675793553,"remaining_time":0.9172609363},
{"learn":[0.03938645449],"iteration":836,"passed_time":4.681253122,"remaining_time":0.9116418863},
{"learn":[0.03933661017],"iteration":837,"passed_time":4.686554076,"remaining_time":0.9059925541},
{"learn":[0.03930823485],"iteration":838,"passed_time":4.692641687,"remaining_time":0.9004950079},
{"learn":[0.03929092828],"iteration":839,"passed_time":4.697748201,"remaining_time":0.8948091812},
{"learn":[0.03924917683],"iteration":840,"passed_time":4.702654011,"remaining_time":0.8890867869},
{"learn":[0.03917814815],"iteration":841,"passed_time":4.708118063,"remaining_time":0.8834710854},
{"learn":[0.03917186274],"iteration":842,"passed_time":4.713517889,"remaining_time":0.8778437824},
{"learn":[0.03916549086],"iteration":843,"passed_time":4.718804839,"remaining_time":0.872196155},
{"learn":[0.03915732403],"iteration":844,"passed_time":4.724818937,"remaining_time":0.8666827637},
{"learn":[0.03915207635],"iteration":845,"passed_time":4.729500213,"remaining_time":0.8609255706},
{"learn":[0.03913859677],"iteration":846,"passed_time":4.733775281,"remaining_time":0.8550975419},
{"learn":[0.0391359938],"iteration":847,"passed_time":4.738132538,"remaining_time":0.8492879078},
{"learn":[0.03905375485],"iteration":848,"passed_time":4.744018966,"remaining_time":0.8437536676},
{"learn":[0.03903301883],"iteration":849,"passed_time":4.750214602,"remaining_time":0.8382731651},
{"learn":[0.03896025265],"iteration":850,"passed_time":4.754840064,"remaining_time":0.8325160629},
{"learn":[0.03894544035],"iteration":851,"passed_time":4.760692417,"remaining_time":0.8269747391},
{"learn":[0.03889543806],"iteration":852,"passed_time":4.765833039,"remaining_time":0.8213100314},
{"learn":[0.03885697126],"iteration":853,"passed_time":4.772007752,"remaining_time":0.8158233393},
{"learn":[0.03882893441],"iteration":854,"passed_time":4.777447972,"remaining_time":0.8102104749},
{"learn":[0.03875660529],"iteration":855,"passed_time":4.783783766,"remaining_time":0.8047486708},
{"learn":[0.03868716399],"iteration":856,"passed_time":4.790346887,"remaining_time":0.7993227595},
{"learn":[0.03864346204],"iteration":857,"passed_time":4.795304414,"remaining_time":0.7936284694},
{"learn":[0.03854832592],"iteration":858,"passed_time":4.800277211,"remaining_time":0.7879384013},
{"learn":[0.03853071929],"iteration":859,"passed_time":4.805521996,"remaining_time":0.7822942784},
{"learn":[0.0384421201],"iteration":860,"passed_time":4.810646272,"remaining_time":0.7766316281},
{"learn":[0.03839125867],"iteration":861,"passed_time":4.816928782,"remaining_time":0.7711556519},
{"learn":[0.03832862472],"iteration":862,"passed_time":4.822847301,"remaining_time":0.7656200234},
{"learn":[0.03832563393],"iteration":863,"passed_time":4.828095697,"remaining_time":0.7599780264},
{"learn":[0.03824810441],"iteration":864,"passed_time":4.834146809,"remaining_time":0.7544622187},
{"learn":[0.0382178139],"iteration":865,"passed_time":4.84059125,"remaining_time":0.7490060363},
{"learn":[0.03821467926],"iteration":866,"passed_time":4.844840866,"remaining_time":0.7432108825},
{"learn":[0.03817794269],"iteration":867,"passed_time":4.850147897,"remaining_time":0.737580095},
{"learn":[0.03809283635],"iteration":868,"passed_time":4.856133617,"remaining_time":0.7320523635},
{"learn":[0.0380230746],"iteration":869,"passed_time":4.861156052,"remaining_time":0.7263796399},
{"learn":[0.03799947271],"iteration":870,"passed_time":4.866547193,"remaining_time":0.7207630171},
{"learn":[0.03798882708],"iteration":871,"passed_time":4.871690564,"remaining_time":0.7151105416},
{"learn":[0.03791223432],"iteration":872,"passed_time":4.876627379,"remaining_time":0.7094291834},
{"learn":[0.03783089462],"iteration":873,"passed_time":4.882408535,"remaining_time":0.7038712533},
{"learn":[0.03780567004],"iteration":874,"passed_time":4.889089382,"remaining_time":0.6984413402},
{"learn":[0.03772544398],"iteration":875,"passed_time":4.895108493,"remaining_time":0.6929149008},
{"learn":[0.03766612932],"iteration":876,"passed_time":4.900373786,"remaining_time":0.6872816142},
{"learn":[0.03762771887],"iteration":877,"passed_time":4.906332737,"remaining_time":0.6817455511},
{"learn":[0.03757533988],"iteration":878,"passed_time":4.912042825,"remaining_time":0.6761742683},
{"learn":[0.03757215544],"iteration":879,"passed_time":4.916467186,"remaining_time":0.6704273435},
{"learn":[0.03751930035],"iteration":880,"passed_time":4.922653249,"remaining_time":0.664921381},
{"learn":[0.03748642655],"iteration":881,"passed_time":4.927933028,"remaining_time":0.6592926273},
{"learn":[0.03748310094],"iteration":882,"passed_time":4.933421836,"remaining_time":0.6536923611},
{"learn":[0.03748074328],"iteration":883,"passed_time":4.939697971,"remaining_time":0.6481956614},
{"learn":[0.0374187922],"iteration":884,"passed_time":4.945877135,"remaining_time":0.6426845995},
{"learn":[0.03735534864],"iteration":885,"passed_time":4.951785689,"remaining_time":0.6371372105},
{"learn":[0.03731740968],"iteration":886,"passed_time":4.957607855,"remaining_time":0.6315780018},
{"learn":[0.03728483137],"iteration":887,"passed_time":4.96402428,"remaining_time":0.6260931525},
{"learn":[0.03722535393],"iteration":888,"passed_time":4.970580491,"remaining_time":0.6206236608},
{"learn":[0.03722217874],"iteration":889,"passed_time":4.978376499,"remaining_time":0.6153049606},
{"learn":[0.0371384581],"iteration":890,"passed_time":4.985258699,"remaining_time":0.6098689093},
{"learn":[0.03705843648],"iteration":891,"passed_time":4.990463836,"remaining_time":0.6042265631},
{"learn":[0.03705515362],"iteration":892,"passed_time":4.995534468,"remaining_time":0.5985690796},
{"learn":[0.03700043507],"iteration":893,"passed_time":5.001208454,"remaining_time":0.5929844476},
{"learn":[0.03699692665],"iteration":894,"passed_time":5.007887745,"remaining_time":0.5875175567},
{"learn":[0.03696129356],"iteration":895,"passed_time":5.014348644,"remaining_time":0.5820226104},
{"learn":[0.03695505227],"iteration":896,"passed_time":5.020165763,"remaining_time":0.576451587},
{"learn":[0.03686874752],"iteration":897,"passed_time":5.025588746,"remaining_time":0.5708352473},
{"learn":[0.03681719155],"iteration":898,"passed_time":5.032538368,"remaining_time":0.5653908512},
{"learn":[0.0367686135],"iteration":899,"passed_time":5.037975978,"remaining_time":0.5597751086},
{"learn":[0.0367665095],"iteration":900,"passed_time":5.043842447,"remaining_time":0.5542068838},
{"learn":[0.03672107013],"iteration":901,"passed_time":5.048807107,"remaining_time":0.5485400182},
{"learn":[0.03667225022],"iteration":902,"passed_time":5.055528957,"remaining_time":0.5430634649},
{"learn":[0.03661477619],"iteration":903,"passed_time":5.06150628,"remaining_time":0.5375050917},
{"learn":[0.03654611808],"iteration":904,"passed_time":5.06764216,"remaining_time":0.5319624367},
{"learn":[0.03654360895],"iteration":905,"passed_time":5.073171538,"remaining_time":0.5263555459},
{"learn":[0.03646361567],"iteration":906,"passed_time":5.079004479,"remaining_time":0.5207799521},
{"learn":[0.03641200987],"iteration":907,"passed_time":5.085312614,"remaining_time":0.5152519389},
{"learn":[0.03637896326],"iteration":908,"passed_time":5.091639656,"remaining_time":0.509724102},
{"learn":[0.03634116003],"iteration":909,"passed_time":5.09739974,"remaining_time":0.5041384359},
{"learn":[0.0362613171],"iteration":910,"passed_time":5.102901386,"remaining_time":0.4985271387},
{"learn":[0.03618696164],"iteration":911,"passed_time":5.108666426,"remaining_time":0.4929414972},
{"learn":[0.03614287149],"iteration":912,"passed_time":5.113211486,"remaining_time":0.4872392106},
{"learn":[0.03609777045],"iteration":913,"passed_time":5.118416222,"remaining_time":0.4816015263},
{"learn":[0.03607388987],"iteration":914,"passed_time":5.124413482,"remaining_time":0.4760384109},
{"learn":[0.0360516482],"iteration":915,"passed_time":5.12971567,"remaining_time":0.4704106073},
{"learn":[0.03600998406],"iteration":916,"passed_time":5.135532326,"remaining_time":0.4648300797},
{"learn":[0.03591964043],"iteration":917,"passed_time":5.141893612,"remaining_time":0.4592976864},
{"learn":[0.03587517334],"iteration":918,"passed_time":5.147154193,"remaining_time":0.453666474},
{"learn":[0.03580454933],"iteration":919,"passed_time":5.152014008,"remaining_time":0.4480012181},
{"learn":[0.03580173067],"iteration":920,"passed_time":5.157802937,"remaining_time":0.4424174072},
{"learn":[0.03579875344],"iteration":921,"passed_time":5.16375979,"remaining_time":0.4368473575},
{"learn":[0.03575414448],"iteration":922,"passed_time":5.168402585,"remaining_time":0.4311668462},
{"learn":[0.03573921641],"iteration":923,"passed_time":5.173800682,"remaining_time":0.4255507055},
{"learn":[0.03569930255],"iteration":924,"passed_time":5.179544176,"remaining_time":0.4199630413},
{"learn":[0.03567019823],"iteration":925,"passed_time":5.185300802,"remaining_t,
{"learn":[0.03,
{"learn":[0.03566483809],"iteration":926,"passed_time":5.19141054,"remaining_time":0.4088165797},
{"learn":[0.03566332695],"iteration":927,"passed_time":5.198082891,"remaining_time":0.4032995347},
{"learn":[0.03558966933],"iteration":928,"passed_time":5.204173124,"remaining_time":0.3977355133},
{"learn":[0.03556232655],"iteration":929,"passed_time":5.210329084,"remaining_time":0.3921753074},
{"learn":[0.03550129787],"iteration":930,"passed_time":5.2176249,"remaining_time":0.3866983008},
{"learn":[0.0354203407],"iteration":931,"passed_time":5.223322528,"remaining_time":0.3811007853},
{"learn":[0.03537991982],"iteration":932,"passed_time":5.22841035,"remaining_time":0.3754592642},
{"learn":[0.03537603009],"iteration":933,"passed_time":5.23448586,"remaining_time":0.3698887224},
{"learn":[0.03535593917],"iteration":934,"passed_time":5.240037063,"remaining_time":0.3642806515},
{"learn":[0.03535320677],"iteration":935,"passed_time":5.245171288,"remaining_time":0.3586441907},
{"learn":[0.03527707332],"iteration":936,"passed_time":5.251219533,"remaining_time":0.3530702567},
{"learn":[0.03522687796],"iteration":937,"passed_time":5.25747498,"remaining_time":0.3475090072},
{"learn":[0.03515539102],"iteration":938,"passed_time":5.262662251,"remaining_time":0.3418768875},
{"learn":[0.03511060097],"iteration":939,"passed_time":5.269184051,"remaining_time":0.3363308969},
{"learn":[0.03508461963],"iteration":940,"passed_time":5.275468468,"remaining_time":0.3307679486},
{"learn":[0.03508077933],"iteration":941,"passed_time":5.281121287,"remaining_time":0.3251645803},
{"learn":[0.03504723568],"iteration":942,"passed_time":5.287611754,"remaining_time":0.3196117391},
{"learn":[0.03499684913],"iteration":943,"passed_time":5.292432192,"remaining_time":0.3139578419},
{"learn":[0.03499123478],"iteration":944,"passed_time":5.298173997,"remaining_time":0.3083593331},
{"learn":[0.03498810175],"iteration":945,"passed_time":5.304326675,"remaining_time":0.3027839751},
{"learn":[0.0349181262],"iteration":946,"passed_time":5.309415058,"remaining_time":0.2971478332},
{"learn":[0.034897571],"iteration":947,"passed_time":5.315641663,"remaining_time":0.2915752811},
{"learn":[0.03489228331],"iteration":948,"passed_time":5.321622062,"remaining_time":0.2859881192},
{"learn":[0.03481240144],"iteration":949,"passed_time":5.326957017,"remaining_time":0.2803661588},
{"learn":[0.03476757925],"iteration":950,"passed_time":5.332142588,"remaining_time":0.274737105},
{"learn":[0.0347645095],"iteration":951,"passed_time":5.338401464,"remaining_time":0.269163099},
{"learn":[0.03472726613],"iteration":952,"passed_time":5.343577486,"remaining_time":0.2635342517},
{"learn":[0.03466780384],"iteration":953,"passed_time":5.349207277,"remaining_time":0.2579282335},
{"learn":[0.03464584806],"iteration":954,"passed_time":5.354609944,"remaining_time":0.2523114633},
{"learn":[0.03461566643],"iteration":955,"passed_time":5.36056823,"remaining_time":0.2467207135},
{"learn":[0.03458716962],"iteration":956,"passed_time":5.365871301,"remaining_time":0.2410997554},
{"learn":[0.03458483119],"iteration":957,"passed_time":5.372362499,"remaining_time":0.2355315501},
{"learn":[0.03456807698],"iteration":958,"passed_time":5.378830991,"remaining_tim,
{"learn":[0.0,
{"learn":[0.03448451069],"iteration":959,"passed_time":5.383564515,"remaining_time,
{"learn":[0.0,
{"learn":[0.03443747263],"iteration":960,"passed_time":5.38981771,"remaining_time",
{"learn":[0.,
{"learn":[0.03441662726],"iteration":961,"passed_time":5.396365142,"remaining_time",
{"learn":[0.,
{"learn":[0.03434923033],"iteration":962,"passed_time":5.402853931,"remaining_time,
{"learn":[0.0,
{"learn":[0.034324655],"iteration":963,"passed_time":5.407934372,"remaining_time":,
{"learn":[0,
{"learn":[0.03428389293],"iteration":964,"passed_time":5.415899032,"remaining_time":,
{"learn":[0,
{"learn":[0.03421945168],"iteration":965,"passed_time":5.420999995,"remaining_time":,
{"learn":[0,
{"learn":[0.03416453379],"iteration":966,"passed_time":5.426944668,"remaining_time":,
{"learn":[0,
{"learn":[0.03414335368],"iteration":967,"passed_time":5.432622634,"remaining_time":,
{"learn":[0,
{"learn":[0.03411153745],"iteration":968,"passed_time":5.438569271,"remaining_time":,
{"learn":[0,
{"learn":[0.03404471847],"iteration":969,"passed_time":5.444463932,"remaining_time":,
{"learn":[0,
{"learn":[0.03398723265],"iteration":970,"passed_time":5.45220784,"remaining_time":,
{"learn":[0,
{"learn":[0.03392700304],"iteration":971,"passed_time":5.459962501,"remaining_time":,
{"learn":[0,
{"learn":[0.03387688086],"iteration":972,"passed_time":5.466364457,"remaining_time":,
{"learn":[0,
{"learn":[0.03381503811],"iteration":973,"passed_time":5.473025689,"remaining_time":,
{"learn":[,
{"learn":[0.03381329154],"iteration":974,"passed_time":5.478503538,"remaining_time":,
{"learn":[0,
{"learn":[0.03373504796],"iteration":975,"passed_time":5.48354774,"remaining_time":,
{"learn":[0,
{"learn":[0.03367302879],"iteration":976,"passed_time":5.490113621,"remaining_time,
{"learn":[0.0,
{"learn":[0.03362275613],"iteration":977,"passed_time":5.49543419,"remaining_time",
{"learn":[0,
{"learn":[0.03362076235],"iteration":978,"passed_time":5.501257745,"remaining_time":,
{"learn":[0,
{"learn":[0.03356010158],"iteration":979,"passed_time":5.508195363,"remaining_tim,
{"learn":[0.03,
{"learn":[0.0334849028],"iteration":980,"passed_time":5.514185424,"remaining_time,
{"learn":[0.0,
{"learn":[0.03346157279],"iteration":981,"passed_time":5.519630972,"remaining_time,
{"learn":[0.0,
{"learn":[0.03339984144],"iteration":982,"passed_time":5.5263957,"remaining_time":0,
{"learn":[0,
{"learn":[0.03337532872],"iteration":983,"passed_time":5.533001396,"remaining_time":0.08996750238},
{"learn":[0.03334979095],"iteration":984,"passed_time":5.537799831,"remaining_time":0.08433197712},
{"learn":[0.03330122459],"iteration":985,"passed_time":5.543209772,"remaining_time":0.07870683246},
{"learn":[0.03325677888],"iteration":986,"passed_time":5.548818777,"remaining_time":0.07308474579},
{"learn":[0.03322623796],"iteration":987,"passed_time":5.554118471,"remaining_time":0.0674589288},
{"learn":[0.03318316196],"iteration":988,"passed_time":5.560123917,"remaining_time":0.06184162092},
{"learn":[0.03318120047],"iteration":989,"passed_time":5.566210417,"remaining_time":0.05622434765},
{"learn":[0.03317880851],"iteration":990,"passed_time":5.572023779,"remaining_time":0.05060364683},
{"learn":[0.03317712433],"iteration":991,"passed_time":5.576460761,"remaining_time":0.04497145775},
{"learn":[0.03315051737],"iteration":992,"passed_time":5.581287612,"remaining_time":0.03934442425},
{"learn":[0.03310000357],"iteration":993,"passed_time":5.585937681,"remaining_time":0.03371793369},
{"learn":[0.03300720532],"iteration":994,"passed_time":5.590604132,"remaining_time":0.0280934881},
{"learn":[0.03295204989],"iteration":995,"passed_time":5.593996431,"remaining_time":0.02246584912},
{"learn":[0.03292469739],"iteration":996,"passed_time":5.598637284,"remaining_time":0.0168464512},
{"learn":[0.03291656586],"iteration":997,"passed_time":5.601862498,"remaining_time":0.01122617735},
{"learn":[0.03285245415],"iteration":998,"passed_time":5.605406335,"remaining_time":0.005611017352},
{"learn":[0.03281081676],"iteration":999,"passed_time":5.608561364,"remaining_time":0}
]}